lab02/src/simple_counter.sv
`timescale 1ns / 1ps
`default_nettype none
module simple_counter(  input wire          clk_in,
                        input wire          rst_in,
                        input wire          evt_in,
                        output logic[15:0]  count_out
                    );

  always_ff @(posedge clk_in) begin
    if (rst_in) begin
      count_out <= 16'b0;
    end else begin
      /* When evt_in is high on rising clk_in, increase the count by one */
      if (evt_in) begin
	count_out <= count_out + 1;
      end
    end
  end
endmodule
`default_nettype wire

lab02/sim/simple_counter_tb.sv
`timescale 1ns / 1ps

module simple_counter_tb;

  /* logics for inputs and outputs */
  logic clk_in;
  logic rst_in;
  logic evt_in;
  logic[15:0] count_out;  /* be sure this is the right bit width! */

  simple_counter my_counter(  .clk_in(clk_in),
                              .rst_in(rst_in),
                              .evt_in(evt_in),
                              .count_out(count_out));

  /* An always block in simulation **always** runs in the background.
   * This is useful to simulate a clock for sequential testbenches:
   *	- every 5ns, make clk be !clk
   */
  always begin
  	#5
  	clk_in = !clk_in;
  end

  /* Make sure to initialize the clock as well! */
  initial begin
  	clk_in = 0;
  end

  /* Finally, the actual test */
  initial begin

    /* Set up GTKWave output
     *
     * We would like to dump the results of this simulation
     * to the waveform file "counter.vcd" - change this if you
     * would like.
     *
     * We would like to show variables from the module
     * 'simple_counter_tb'. If you are dumping variables from
     * a different module, be sure to change this to the name
     * of the module you're trying to examine.
     *
     * That zero there means "dump all the variables from this
     * module plus anything it instantiates"
     */
    $dumpfile("counter.vcd");
    $dumpvars(0, simple_counter_tb);

    /* Initialize inputs, say hi (super important)
     * Then wait for things to settle down
     */
    $display("Starting Sim");
    rst_in = 0;
    evt_in = 0;
    #20

    /* Reset... */
    rst_in = 1; //reset system
    #20;
    rst_in=0; //pull low
    #20;


    /* Make something happen - pulse evt for a clock cycle */
    evt_in = 1;
    #10
    evt_in = 0;

    /* Make another thing happen several clock cycles later
     * then let it run for a bit (:
     */
    #50

    evt_in = 1;
    #200
    evt_in = 0;

    /* One more time - this time we reset while evt_in is high
     * Ensure that count_out is zero after we assert rst_in!
     */
    #200

    evt_in = 1;
    #50
    rst_in = 1;

    #50
    $finish;
  end
endmodule /* simple_counter_tb */

lab02/counter.vcd
$date
	Thu Sep 22 08:47:51 2022
$end
$version
	Icarus Verilog
$end
$timescale
	1ps
$end
$scope module simple_counter_tb $end
$var wire 16 ! count_out [15:0] $end
$var reg 1 " clk_in $end
$var reg 1 # evt_in $end
$var reg 1 $ rst_in $end
$scope module my_counter $end
$var wire 1 " clk_in $end
$var wire 1 # evt_in $end
$var wire 1 $ rst_in $end
$var reg 16 % count_out [15:0] $end
$upscope $end
$upscope $end
$enddefinitions $end
#0
$dumpvars
bx %
0$
0#
0"
bx !
$end
#5000
1"
#10000
0"
#15000
1"
#20000
0"
1$
#25000
b0 !
b0 %
1"
#30000
0"
#35000
1"
#40000
0"
0$
#45000
1"
#50000
0"
#55000
1"
#60000
0"
1#
#65000
b1 !
b1 %
1"
#70000
0"
0#
#75000
1"
#80000
0"
#85000
1"
#90000
0"
#95000
1"
#100000
0"
#105000
1"
#110000
0"
#115000
1"
#120000
0"
1#
#125000
b10 !
b10 %
1"
#130000
0"
#135000
b11 !
b11 %
1"
#140000
0"
#145000
b100 !
b100 %
1"
#150000
0"
#155000
b101 !
b101 %
1"
#160000
0"
#165000
b110 !
b110 %
1"
#170000
0"
#175000
b111 !
b111 %
1"
#180000
0"
#185000
b1000 !
b1000 %
1"
#190000
0"
#195000
b1001 !
b1001 %
1"
#200000
0"
#205000
b1010 !
b1010 %
1"
#210000
0"
#215000
b1011 !
b1011 %
1"
#220000
0"
#225000
b1100 !
b1100 %
1"
#230000
0"
#235000
b1101 !
b1101 %
1"
#240000
0"
#245000
b1110 !
b1110 %
1"
#250000
0"
#255000
b1111 !
b1111 %
1"
#260000
0"
#265000
b10000 !
b10000 %
1"
#270000
0"
#275000
b10001 !
b10001 %
1"
#280000
0"
#285000
b10010 !
b10010 %
1"
#290000
0"
#295000
b10011 !
b10011 %
1"
#300000
0"
#305000
b10100 !
b10100 %
1"
#310000
0"
#315000
b10101 !
b10101 %
1"
#320000
0"
0#
#325000
1"
#330000
0"
#335000
1"
#340000
0"
#345000
1"
#350000
0"
#355000
1"
#360000
0"
#365000
1"
#370000
0"
#375000
1"
#380000
0"
#385000
1"
#390000
0"
#395000
1"
#400000
0"
#405000
1"
#410000
0"
#415000
1"
#420000
0"
#425000
1"
#430000
0"
#435000
1"
#440000
0"
#445000
1"
#450000
0"
#455000
1"
#460000
0"
#465000
1"
#470000
0"
#475000
1"
#480000
0"
#485000
1"
#490000
0"
#495000
1"
#500000
0"
#505000
1"
#510000
0"
#515000
1"
#520000
0"
1#
#525000
b10110 !
b10110 %
1"
#530000
0"
#535000
b10111 !
b10111 %
1"
#540000
0"
#545000
b11000 !
b11000 %
1"
#550000
0"
#555000
b11001 !
b11001 %
1"
#560000
0"
#565000
b11010 !
b11010 %
1"
#570000
0"
1$
#575000
b0 !
b0 %
1"
