lab02/src/ps2_decoder.sv
module ps2_decoder( input wire clk_in,
  input wire rst_in,
  input wire ps_data_in,
  input wire ps_clk_in,
  output logic [7:0] code_out,
  output logic code_valid_out
);
    logic in_process; // This variable exists for the valid single falling edge
    logic [3:0] counter; // This counter exists to track the sending of data
    logic old; // This exists for edge detection
    logic swi; // Checks if we can or cannot send data

    /* 
    * EDGE DETECTOR BLOCK
    */
    always_ff @(posedge clk_in) begin
	if (rst_in) begin
		old <= 1;
	end else begin
		if (!ps_clk_in && ps_clk_in != old) begin
			in_process <= 1;
			old <= 0;
		end else if (ps_clk_in && ps_clk_in != old) begin
			old <= 1;
		end else begin
			in_process <= 0;
		end
	end
    end

    always_ff @(posedge clk_in) begin
	// If we start, we set the old_clk_ps as default to 0
        if (rst_in) begin
		code_out <= 8'b0000_0000;
		code_valid_out <= 0;
		counter <= 1'b0;
		swi <= 0;
	end else begin
		// If it's the first falling edge, start the counter and the
		// data sending
		if (counter == 0 && in_process) begin
			swi <= 1;
			counter <= counter + 1;
		end

		/*
		* When we are allowed to send data
		*/
		if (swi) begin
			// We only do stuff when encountering the falling edge
			// of the clock
			if (in_process) begin
				counter <= counter + 1;
				// We do not take data from Parity or Stop
				if (counter != 9 && counter != 10) begin
					code_out <= {code_out[6:0], ~ps_data_in};
				end else if (counter == 9) begin
					if (~ps_data_in != (^code_out)) begin
						swi <= 0;
						counter <= 1'b0;
					end
				end else if (counter == 10) begin
					swi <= 0;
					code_valid_out <= 1;
				end
			end
		end

		// This should remain high only for one cycle of the system
		// clock
		if (code_valid_out) begin
			code_valid_out <= 0;
			counter <= 1'b0;
		end
	end
    end
endmodule

lab02/sim/ps2_tb.sv
`timescale 1ns / 1ps
`default_nettype none

module ps2_tb;

  //make logics for inputs and outputs!
  logic clk_in;
  logic rst_in;
  logic ps_data_in;
  logic ps_clk_in;
  logic [7:0] code_out;
  logic code_valid_out;

  logic [10:0] frame = 11'b01011001011;
  ps2_decoder uut(.clk_in(clk_in),
                  .rst_in(rst_in),
                  .ps_data_in(ps_data_in),
                  .ps_clk_in(ps_clk_in),
                  .code_out(code_out),
                  .code_valid_out(code_valid_out)
                );
  always begin
    #5;  //every 5 ns switch...so period of clock is 10 ns...100 MHz clock
    clk_in = !clk_in;
  end

  //initial block...this is our test simulation
  initial begin
    $dumpfile("ps2.vcd"); //file to store value change dump (vcd)
    $dumpvars(0,ps2_tb); //store everything at the current level and below
    $display("Starting Sim"); //print nice message
    clk_in = 0;
    rst_in = 0;
    ps_data_in =1;
    ps_clk_in = 1;
    #20  //wait
    rst_in = 1;
    #20; //hold
    rst_in=0;
    #20;
    $display("PROGRESS");
    for(int i=0; i<11; i=i+1)begin
      ps_clk_in = 1;
      ps_data_in = frame[10-i];
      #100;
      ps_clk_in = 0;
      #100;
      $display("%b", code_out);
    end
    $display("RESULT");
    $display("%h", code_out);
    #600
    $display("PROGRESS");
    for(int i=0; i<11; i=i+1)begin
      ps_clk_in = 1;
      ps_data_in = frame[10-i];
      #100;
      ps_clk_in = 0;
      #100;
      $display("%b", code_out);
    end
    $display("RESULT");
    $display("%h", code_out);
    $finish;

  end
endmodule //counter_tb

`default_nettype wire

lab02/ps2.vcd
$date
	Thu Sep 22 21:48:46 2022
$end
$version
	Icarus Verilog
$end
$timescale
	1ps
$end
$scope module ps2_tb $end
$var wire 1 ! code_valid_out $end
$var wire 8 " code_out [7:0] $end
$var reg 1 # clk_in $end
$var reg 11 $ frame [10:0] $end
$var reg 1 % ps_clk_in $end
$var reg 1 & ps_data_in $end
$var reg 1 ' rst_in $end
$scope module uut $end
$var wire 1 # clk_in $end
$var wire 1 % ps_clk_in $end
$var wire 1 & ps_data_in $end
$var wire 1 ' rst_in $end
$var reg 8 ( code_out [7:0] $end
$var reg 1 ! code_valid_out $end
$var reg 4 ) counter [3:0] $end
$var reg 1 * in_process $end
$var reg 1 + old $end
$var reg 1 , swi $end
$upscope $end
$scope begin $ivl_for_loop0 $end
$var integer 32 - i [31:0] $end
$upscope $end
$scope begin $ivl_for_loop1 $end
$var integer 32 . i [31:0] $end
$upscope $end
$upscope $end
$enddefinitions $end
#0
$dumpvars
b0 .
b0 -
x,
x+
x*
bx )
bx (
0'
1&
1%
b1011001011 $
0#
bx "
x!
$end
#5000
0*
1#
#10000
0#
#15000
1#
#20000
0#
1'
#25000
1+
0,
b0 )
0!
b0 "
b0 (
1#
#30000
0#
#35000
1#
#40000
0#
0'
#45000
1#
#50000
0#
#55000
1#
#60000
0#
0&
#65000
1#
#70000
0#
#75000
1#
#80000
0#
#85000
1#
#90000
0#
#95000
1#
#100000
0#
#105000
1#
#110000
0#
#115000
1#
#120000
0#
#125000
1#
#130000
0#
#135000
1#
#140000
0#
#145000
1#
#150000
0#
#155000
1#
#160000
0#
0%
#165000
0+
1*
1#
#170000
0#
#175000
b1 )
1,
0*
1#
#180000
0#
#185000
1#
#190000
0#
#195000
1#
#200000
0#
#205000
1#
#210000
0#
#215000
1#
#220000
0#
#225000
1#
#230000
0#
#235000
1#
#240000
0#
#245000
1#
#250000
0#
#255000
1#
#260000
0#
1&
1%
b1 -
#265000
1+
1#
#270000
0#
#275000
1#
#280000
0#
#285000
1#
#290000
0#
#295000
1#
#300000
0#
#305000
1#
#310000
0#
#315000
1#
#320000
0#
#325000
1#
#330000
0#
#335000
1#
#340000
0#
#345000
1#
#350000
0#
#355000
1#
#360000
0#
0%
#365000
0+
1*
1#
#370000
0#
#375000
b10 )
0*
1#
#380000
0#
#385000
1#
#390000
0#
#395000
1#
#400000
0#
#405000
1#
#410000
0#
#415000
1#
#420000
0#
#425000
1#
#430000
0#
#435000
1#
#440000
0#
#445000
1#
#450000
0#
#455000
1#
#460000
0#
0&
1%
b10 -
#465000
1+
1#
#470000
0#
#475000
1#
#480000
0#
#485000
1#
#490000
0#
#495000
1#
#500000
0#
#505000
1#
#510000
0#
#515000
1#
#520000
0#
#525000
1#
#530000
0#
#535000
1#
#540000
0#
#545000
1#
#550000
0#
#555000
1#
#560000
0#
0%
#565000
0+
1*
1#
#570000
0#
#575000
b1 "
b1 (
b11 )
0*
1#
#580000
0#
#585000
1#
#590000
0#
#595000
1#
#600000
0#
#605000
1#
#610000
0#
#615000
1#
#620000
0#
#625000
1#
#630000
0#
#635000
1#
#640000
0#
#645000
1#
#650000
0#
#655000
1#
#660000
0#
1&
1%
b11 -
#665000
1+
1#
#670000
0#
#675000
1#
#680000
0#
#685000
1#
#690000
0#
#695000
1#
#700000
0#
#705000
1#
#710000
0#
#715000
1#
#720000
0#
#725000
1#
#730000
0#
#735000
1#
#740000
0#
#745000
1#
#750000
0#
#755000
1#
#760000
0#
0%
#765000
0+
1*
1#
#770000
0#
#775000
b10 "
b10 (
b100 )
0*
1#
#780000
0#
#785000
1#
#790000
0#
#795000
1#
#800000
0#
#805000
1#
#810000
0#
#815000
1#
#820000
0#
#825000
1#
#830000
0#
#835000
1#
#840000
0#
#845000
1#
#850000
0#
#855000
1#
#860000
0#
1%
b100 -
#865000
1+
1#
#870000
0#
#875000
1#
#880000
0#
#885000
1#
#890000
0#
#895000
1#
#900000
0#
#905000
1#
#910000
0#
#915000
1#
#920000
0#
#925000
1#
#930000
0#
#935000
1#
#940000
0#
#945000
1#
#950000
0#
#955000
1#
#960000
0#
0%
#965000
0+
1*
1#
#970000
0#
#975000
b100 "
b100 (
b101 )
0*
1#
#980000
0#
#985000
1#
#990000
0#
#995000
1#
#1000000
0#
#1005000
1#
#1010000
0#
#1015000
1#
#1020000
0#
#1025000
1#
#1030000
0#
#1035000
1#
#1040000
0#
#1045000
1#
#1050000
0#
#1055000
1#
#1060000
0#
0&
1%
b101 -
#1065000
1+
1#
#1070000
0#
#1075000
1#
#1080000
0#
#1085000
1#
#1090000
0#
#1095000
1#
#1100000
0#
#1105000
1#
#1110000
0#
#1115000
1#
#1120000
0#
#1125000
1#
#1130000
0#
#1135000
1#
#1140000
0#
#1145000
1#
#1150000
0#
#1155000
1#
#1160000
0#
0%
#1165000
0+
1*
1#
#1170000
0#
#1175000
b1001 "
b1001 (
b110 )
0*
1#
#1180000
0#
#1185000
1#
#1190000
0#
#1195000
1#
#1200000
0#
#1205000
1#
#1210000
0#
#1215000
1#
#1220000
0#
#1225000
1#
#1230000
0#
#1235000
1#
#1240000
0#
#1245000
1#
#1250000
0#
#1255000
1#
#1260000
0#
1%
b110 -
#1265000
1+
1#
#1270000
0#
#1275000
1#
#1280000
0#
#1285000
1#
#1290000
0#
#1295000
1#
#1300000
0#
#1305000
1#
#1310000
0#
#1315000
1#
#1320000
0#
#1325000
1#
#1330000
0#
#1335000
1#
#1340000
0#
#1345000
1#
#1350000
0#
#1355000
1#
#1360000
0#
0%
#1365000
0+
1*
1#
#1370000
0#
#1375000
b10011 "
b10011 (
b111 )
0*
1#
#1380000
0#
#1385000
1#
#1390000
0#
#1395000
1#
#1400000
0#
#1405000
1#
#1410000
0#
#1415000
1#
#1420000
0#
#1425000
1#
#1430000
0#
#1435000
1#
#1440000
0#
#1445000
1#
#1450000
0#
#1455000
1#
#1460000
0#
1&
1%
b111 -
#1465000
1+
1#
#1470000
0#
#1475000
1#
#1480000
0#
#1485000
1#
#1490000
0#
#1495000
1#
#1500000
0#
#1505000
1#
#1510000
0#
#1515000
1#
#1520000
0#
#1525000
1#
#1530000
0#
#1535000
1#
#1540000
0#
#1545000
1#
#1550000
0#
#1555000
1#
#1560000
0#
0%
#1565000
0+
1*
1#
#1570000
0#
#1575000
b100110 "
b100110 (
b1000 )
0*
1#
#1580000
0#
#1585000
1#
#1590000
0#
#1595000
1#
#1600000
0#
#1605000
1#
#1610000
0#
#1615000
1#
#1620000
0#
#1625000
1#
#1630000
0#
#1635000
1#
#1640000
0#
#1645000
1#
#1650000
0#
#1655000
1#
#1660000
0#
0&
1%
b1000 -
#1665000
1+
1#
#1670000
0#
#1675000
1#
#1680000
0#
#1685000
1#
#1690000
0#
#1695000
1#
#1700000
0#
#1705000
1#
#1710000
0#
#1715000
1#
#1720000
0#
#1725000
1#
#1730000
0#
#1735000
1#
#1740000
0#
#1745000
1#
#1750000
0#
#1755000
1#
#1760000
0#
0%
#1765000
0+
1*
1#
#1770000
0#
#1775000
b1001101 "
b1001101 (
b1001 )
0*
1#
#1780000
0#
#1785000
1#
#1790000
0#
#1795000
1#
#1800000
0#
#1805000
1#
#1810000
0#
#1815000
1#
#1820000
0#
#1825000
1#
#1830000
0#
#1835000
1#
#1840000
0#
#1845000
1#
#1850000
0#
#1855000
1#
#1860000
0#
1&
1%
b1001 -
#1865000
1+
1#
#1870000
0#
#1875000
1#
#1880000
0#
#1885000
1#
#1890000
0#
#1895000
1#
#1900000
0#
#1905000
1#
#1910000
0#
#1915000
1#
#1920000
0#
#1925000
1#
#1930000
0#
#1935000
1#
#1940000
0#
#1945000
1#
#1950000
0#
#1955000
1#
#1960000
0#
0%
#1965000
0+
1*
1#
#1970000
0#
#1975000
b1010 )
0*
1#
#1980000
0#
#1985000
1#
#1990000
0#
#1995000
1#
#2000000
0#
#2005000
1#
#2010000
0#
#2015000
1#
#2020000
0#
#2025000
1#
#2030000
0#
#2035000
1#
#2040000
0#
#2045000
1#
#2050000
0#
#2055000
1#
#2060000
0#
1%
b1010 -
#2065000
1+
1#
#2070000
0#
#2075000
1#
#2080000
0#
#2085000
1#
#2090000
0#
#2095000
1#
#2100000
0#
#2105000
1#
#2110000
0#
#2115000
1#
#2120000
0#
#2125000
1#
#2130000
0#
#2135000
1#
#2140000
0#
#2145000
1#
#2150000
0#
#2155000
1#
#2160000
0#
0%
#2165000
0+
1*
1#
#2170000
0#
#2175000
1!
0,
b1011 )
0*
1#
#2180000
0#
#2185000
b0 )
0!
1#
#2190000
0#
#2195000
1#
#2200000
0#
#2205000
1#
#2210000
0#
#2215000
1#
#2220000
0#
#2225000
1#
#2230000
0#
#2235000
1#
#2240000
0#
#2245000
1#
#2250000
0#
#2255000
1#
#2260000
0#
b1011 -
