lab05/src/aggregate.sv
`default_nettype none
`timescale 1ns / 1ps

module aggregate(
    input wire clk,
    input wire rst,
    input wire axiiv,
    input wire [1:0] axiid,

    output logic axiov,
    output logic [31:0] axiod
);

    logic [31:0] address = 32'h0;
    logic [31:0] counter;
    logic flag;

    assign axiov = (counter >= 32 && !flag) ? axiiv : 1'b0;
    assign axiod = (counter >= 32) ? address : 2'b0;

    always_ff @(posedge clk) begin
        if (rst) begin
            counter <= 0;
            flag <= 1'b0;
        end else begin
            if (axiiv) begin
                counter <= counter + 1;
                if (counter < 16) begin
                    address <= {address[29:0], axiid};
                end else if (counter >= 32) begin
                    flag <= 1'b1;
                end
            end else begin
                flag <= 1'b0;
                address <= 0;
                counter <= 0;
            end
        end
    end
endmodule

`default_nettype wire

lab05/sim/aggregate_tb.sv
`default_nettype none
`timescale 1ns / 1ps

module aggregate_tb;
    logic clk;
    logic rst;
    logic axiiv;
    logic [1:0] axiid;
    logic axiov;
    logic [31:0] axiod;

    aggregate my_aggregate(.clk(clk), .rst(rst), .axiiv(axiiv), .axiid(axiid), .axiov(axiov), .axiod(axiod));

    logic [63:0] placeholder = 64'h0000_0000_0000_0000;
    logic [31:0] test2 = 32'h4353f92c;
    logic [63:0] test3 = 64'h12345678_00000000;
    logic [7:0] segment;

    always begin
        #10;
        clk = !clk;
    end

    initial begin
        $dumpfile("aggregate.vcd");
        $dumpvars(0, aggregate_tb);
        $display("Starting Sim");
        clk = 0;
        rst = 0;
        #20;
        rst = 1;
        #20;
        rst = 0;
        #20;
        // --------------------------------------------------------------------------------------------------
        // TEST 1: tiny 1-bit message
        // --------------------------------------------------------------------------------------------------
        // #20;
        // axiiv = 1'b1;
        // axiid = 2'b10;
        // #20;
        // axiiv = 1'b0;
        // #20;
        // for (int i = 63; i > 0; i = i - 8) begin
        //     segment = test1[i -: 8];
        //     for (int j = 7; j > 0; j = j - 2) begin
        //         case(j) 
        //             7: axiid = {segment[6], segment[7]};
        //             5: axiid = {segment[4], segment[5]};
        //             3: axiid = {segment[2], segment[3]};
        //             1: axiid = {segment[0], segment[1]};
        //             default: begin end
        //         endcase
        //         #20;
        //     end
        // end
        // axiiv = 1'b0;
        // #400;
        // --------------------------------------------------------------------------------------------------
        // TEST 1: tiny 1-bit message
        // --------------------------------------------------------------------------------------------------

        // --------------------------------------------------------------------------------------------------
        // TEST 2: 32-bit message (no FCS)  
        // --------------------------------------------------------------------------------------------------
        // #20;
        // axiiv = 1'b1;
        // for (int i = 31; i > 0; i = i - 8) begin
        //     segment = test2[i -: 8];
        //     for (int j = 7; j > 0; j = j - 2) begin
        //         case(j) 
        //             7: axiid = {segment[6], segment[7]};
        //             5: axiid = {segment[4], segment[5]};
        //             3: axiid = {segment[2], segment[3]};
        //             1: axiid = {segment[0], segment[1]};
        //             default: begin end
        //         endcase
        //         #20;
        //     end
        // end
        // axiiv = 1'b0;
        // #400;
        // --------------------------------------------------------------------------------------------------
        // TEST 2: 32-bit message (no FCS)  
        // --------------------------------------------------------------------------------------------------

        // --------------------------------------------------------------------------------------------------
        // TEST 3: 32-bit message (with FCS) 
        // --------------------------------------------------------------------------------------------------
        #20;
        axiiv = 1'b1;
        for (int i = 63; i > 0; i = i - 8) begin
            segment = test3[i -: 8];
            for (int j = 7; j > 0; j = j - 2) begin
                case(j) 
                    7: axiid = {segment[6], segment[7]};
                    5: axiid = {segment[4], segment[5]};
                    3: axiid = {segment[2], segment[3]};
                    1: axiid = {segment[0], segment[1]};
                    default: begin end
                endcase
                #20;
            end
        end
        axiiv = 1'b0;
        #400;
        // --------------------------------------------------------------------------------------------------
        // TEST 3: 32-bit message (with FCS) 
        // --------------------------------------------------------------------------------------------------

        $display("Finishing Sim");
        $finish;
    end

endmodule

`default_nettype wire

lab05/aggregate.vcd
$date
	Fri Oct 28 12:52:28 2022
$end
$version
	Icarus Verilog
$end
$timescale
	1ps
$end
$scope module aggregate_tb $end
$var wire 1 ! axiov $end
$var wire 32 " axiod [31:0] $end
$var reg 2 # axiid [1:0] $end
$var reg 1 $ axiiv $end
$var reg 1 % clk $end
$var reg 64 & placeholder [63:0] $end
$var reg 1 ' rst $end
$var reg 8 ( segment [7:0] $end
$var reg 32 ) test2 [31:0] $end
$var reg 64 * test3 [63:0] $end
$scope module my_aggregate $end
$var wire 2 + axiid [1:0] $end
$var wire 1 $ axiiv $end
$var wire 1 % clk $end
$var wire 1 ' rst $end
$var wire 1 ! axiov $end
$var wire 32 , axiod [31:0] $end
$var reg 32 - address [31:0] $end
$var reg 32 . counter [31:0] $end
$var reg 1 / flag $end
$upscope $end
$scope begin $ivl_for_loop0 $end
$var integer 32 0 i [31:0] $end
$scope begin $ivl_for_loop1 $end
$var integer 32 1 j [31:0] $end
$upscope $end
$upscope $end
$upscope $end
$enddefinitions $end
#0
$dumpvars
b0 1
b0 0
x/
bx .
b0 -
b0 ,
bx +
b1001000110100010101100111100000000000000000000000000000000000 *
b1000011010100111111100100101100 )
bx (
0'
b0 &
0%
x$
bx #
b0 "
x!
$end
#10000
0!
b0 .
0/
1%
#20000
0%
1'
#30000
1%
#40000
0%
0'
#50000
1%
#60000
0%
#70000
1%
#80000
0%
b0 #
b0 +
b111 1
b10010 (
b111111 0
1$
#90000
b1 .
1%
#100000
0%
b10 #
b10 +
b101 1
#110000
b10 -
b10 .
1%
#120000
0%
b0 #
b0 +
b11 1
#130000
b1000 -
b11 .
1%
#140000
0%
b1 #
b1 +
b1 1
#150000
b100001 -
b100 .
1%
#160000
0%
b0 #
b0 +
b110100 (
b110111 0
b111 1
#170000
b10000100 -
b101 .
1%
#180000
0%
b11 #
b11 +
b101 1
#190000
b1000010011 -
b110 .
1%
#200000
0%
b10 #
b10 +
b11 1
#210000
b100001001110 -
b111 .
1%
#220000
0%
b0 #
b0 +
b1 1
#230000
b10000100111000 -
b1000 .
1%
#240000
0%
b10 #
b10 +
b1010110 (
b101111 0
b111 1
#250000
b1000010011100010 -
b1001 .
1%
#260000
0%
b101 1
#270000
b100001001110001010 -
b1010 .
1%
#280000
0%
b11 1
#290000
b10000100111000101010 -
b1011 .
1%
#300000
0%
b1 #
b1 +
b1 1
#310000
b1000010011100010101001 -
b1100 .
1%
#320000
0%
b10 #
b10 +
b1111000 (
b100111 0
b111 1
#330000
b100001001110001010100110 -
b1101 .
1%
#340000
0%
b11 #
b11 +
b101 1
#350000
b10000100111000101010011011 -
b1110 .
1%
#360000
0%
b1 #
b1 +
b11 1
#370000
b1000010011100010101001101101 -
b1111 .
1%
#380000
0%
b0 #
b0 +
b1 1
#390000
b100001001110001010100110110100 -
b10000 .
1%
#400000
0%
b0 (
b11111 0
b111 1
#410000
b10001 .
1%
#420000
0%
b101 1
#430000
b10010 .
1%
#440000
0%
b11 1
#450000
b10011 .
1%
#460000
0%
b1 1
#470000
b10100 .
1%
#480000
0%
b10111 0
b111 1
#490000
b10101 .
1%
#500000
0%
b101 1
#510000
b10110 .
1%
#520000
0%
b11 1
#530000
b10111 .
1%
#540000
0%
b1 1
#550000
b11000 .
1%
#560000
0%
b1111 0
b111 1
#570000
b11001 .
1%
#580000
0%
b101 1
#590000
b11010 .
1%
#600000
0%
b11 1
#610000
b11011 .
1%
#620000
0%
b1 1
#630000
b11100 .
1%
#640000
0%
b111 0
b111 1
#650000
b11101 .
1%
#660000
0%
b101 1
#670000
b11110 .
1%
#680000
0%
b11 1
#690000
b11111 .
1%
#700000
0%
b1 1
#710000
1!
b100001001110001010100110110100 "
b100001001110001010100110110100 ,
b100000 .
1%
#720000
0!
0%
0$
b11111111111111111111111111111111 0
b11111111111111111111111111111111 1
#730000
b0 "
b0 ,
b0 .
b0 -
1%
