lab05/src/firewall.sv
`default_nettype none
`timescale 1ns / 1ps

module firewall(
    input wire clk,
    input wire rst,
    input wire axiiv,
    input wire [1:0] axiid,

    output logic axiov,
    output logic [1:0] axiod
);

    logic [47:0] MAC_ADDRESS1 = 48'h69695A065491;
    logic [47:0] MAC_ADDRESS2 = 48'hFFFFFFFFFFFF;
    logic [47:0] address = 48'h0;
    logic [31:0] counter;
    logic flag;

    assign axiov = (flag && counter >= 56) ? axiiv : 1'b0;
    assign axiod = (flag && counter >= 56) ? axiid : 2'b0;

    always_ff @(posedge clk) begin
        if (rst) begin
            counter <= 0;
            flag <= 1'b0;
        end else begin
            if (axiiv) begin
                counter <= counter + 1;
                if (counter < 23) begin
                    address <= {address[45:0], axiid};
                end else if (counter < 48) begin
                    if (counter == 23) begin
                        if ({address[45:0], axiid} == MAC_ADDRESS1 || {address[45:0], axiid} == MAC_ADDRESS2) begin
                            flag <= 1'b1;
                        end
                    end    
                    if (counter == 24) begin
                        if (address == MAC_ADDRESS1 || address == MAC_ADDRESS2) begin
                            flag <= 1'b1;
                        end
                    end                  
                end 
            end else begin
                address <= 0;
                flag <= 1'b0;
                counter <= 0;
            end
        end
    end
endmodule

`default_nettype wire

lab05/sim/firewall_tb.sv
`default_nettype none
`timescale 1ns / 1ps

module firewall_tb;
    logic clk;
    logic rst;
    logic axiiv;
    logic [1:0] axiid;
    logic axiov;
    logic [1:0] axiod;

    firewall my_fw(.clk(clk), .rst(rst), .axiiv(axiiv), .axiid(axiid), .axiov(axiov), .axiod(axiod));

    // Variables for Tests
    logic [47:0] data_address1 = 48'h298D839A21A2;
    logic [47:0] data_address2 = 48'h69695A065490;
    logic [47:0] data_address3 = 48'h69695A165491;
    logic [47:0] data_address4 = 48'h69695A065491;
    logic [47:0] src_address = 48'hFFFFFFFFFFFF;
    logic [15:0] len = 16'h20;
    logic [31:0] message = 32'h1234;
    logic [31:0] fcs = 32'hCBF43926;
    logic [7:0] segment;

    always begin
        #10;
        clk = !clk;
    end

    initial begin
        $dumpfile("firewall.vcd");
        $dumpvars(0, firewall_tb);
        $display("Starting Sim");
        clk = 0;
        rst = 0;
        #20;
        rst = 1;
        #20;
        rst = 0;

        // --------------------------------------------------------------------------------------------------
        // TEST 1: Garbage MAC Address
        // --------------------------------------------------------------------------------------------------
        #20;
        axiiv = 1'b1;
        for (int i = 47; i > 0; i = i - 8) begin
            segment = data_address1[i -: 8];
            for (int j = 7; j > 0; j = j - 2) begin
                case(j)
                    7: axiid = segment[7:6];
                    5: axiid = segment[5:4];
                    3: axiid = segment[3:2];
                    1: axiid = segment[1:0];
                    default: begin end
                endcase
                if (axiov == 1'b1) begin
                    $display("axiov != 0");
                end
                #20;
            end
        end
        for (int i = 47; i > 0; i = i - 8) begin
            segment = src_address[i -: 8];
            for (int j = 7; j > 0; j = j - 2) begin
                case(j)
                    7: axiid = segment[7:6];
                    5: axiid = segment[5:4];
                    3: axiid = segment[3:2];
                    1: axiid = segment[1:0];
                    default: begin end
                endcase
                if (axiov == 1'b1) begin
                    $display("axiov != 0");
                end
                #20;
            end
        end
        for (int i = 15; i > 0; i = i - 8) begin
            segment = len[i -: 8];
            for (int j = 7; j > 0; j = j - 2) begin
                case(j)
                    7: axiid = segment[7:6];
                    5: axiid = segment[5:4];
                    3: axiid = segment[3:2];
                    1: axiid = segment[1:0];
                    default: begin end
                endcase
                if (axiov == 1'b1) begin
                    $display("axiov != 0");
                end
                #20;
            end
        end
        for (int i = 31; i > 0; i = i - 8) begin
            segment = message[i -: 8];
            for (int j = 7; j > 0; j = j - 2) begin
                case(j)
                    7: axiid = segment[7:6];
                    5: axiid = segment[5:4];
                    3: axiid = segment[3:2];
                    1: axiid = segment[1:0];
                    default: begin end
                endcase
                if (axiov == 1'b1) begin
                    $display("axiov != 0");
                end
                #20;
            end
        end
        for (int i = 31; i > 0; i = i - 8) begin
            segment = fcs[i -: 8];
            for (int j = 7; j > 0; j = j - 2) begin
                case(j)
                    7: axiid = segment[7:6];
                    5: axiid = segment[5:4];
                    3: axiid = segment[3:2];
                    1: axiid = segment[1:0];
                    default: begin end
                endcase
                if (axiov == 1'b1) begin
                    $display("axiov != 0");
                end
                #20;
            end
        end
        axiiv = 1'b0;
        $display("PASSED TEST 1!");
        #400;
        // --------------------------------------------------------------------------------------------------
        // TEST 1: Garbage MAC Address
        // --------------------------------------------------------------------------------------------------

        // --------------------------------------------------------------------------------------------------
        // TEST 2: Off-by-one MAC Address
        // --------------------------------------------------------------------------------------------------
        #20;
        axiiv = 1'b1;
        for (int i = 47; i > 0; i = i - 8) begin
            segment = data_address2[i -: 8];
            for (int j = 7; j > 0; j = j - 2) begin
                case(j)
                    7: axiid = segment[7:6];
                    5: axiid = segment[5:4];
                    3: axiid = segment[3:2];
                    1: axiid = segment[1:0];
                    default: begin end
                endcase
                if (axiov == 1'b1) begin
                    $display("axiov != 0");
                end
                #20;
            end
        end
        for (int i = 47; i > 0; i = i - 8) begin
            segment = src_address[i -: 8];
            for (int j = 7; j > 0; j = j - 2) begin
                case(j)
                    7: axiid = segment[7:6];
                    5: axiid = segment[5:4];
                    3: axiid = segment[3:2];
                    1: axiid = segment[1:0];
                    default: begin end
                endcase
                if (axiov == 1'b1) begin
                    $display("axiov != 0");
                end
                #20;
            end
        end
        for (int i = 15; i > 0; i = i - 8) begin
            segment = len[i -: 8];
            for (int j = 7; j > 0; j = j - 2) begin
                case(j)
                    7: axiid = segment[7:6];
                    5: axiid = segment[5:4];
                    3: axiid = segment[3:2];
                    1: axiid = segment[1:0];
                    default: begin end
                endcase
                if (axiov == 1'b1) begin
                    $display("axiov != 0");
                end
                #20;
            end
        end
        for (int i = 31; i > 0; i = i - 8) begin
            segment = message[i -: 8];
            for (int j = 7; j > 0; j = j - 2) begin
                case(j)
                    7: axiid = segment[7:6];
                    5: axiid = segment[5:4];
                    3: axiid = segment[3:2];
                    1: axiid = segment[1:0];
                    default: begin end
                endcase
                if (axiov == 1'b1) begin
                    $display("axiov != 0");
                end
                #20;
            end
        end
        for (int i = 31; i > 0; i = i - 8) begin
            segment = fcs[i -: 8];
            for (int j = 7; j > 0; j = j - 2) begin
                case(j)
                    7: axiid = segment[7:6];
                    5: axiid = segment[5:4];
                    3: axiid = segment[3:2];
                    1: axiid = segment[1:0];
                    default: begin end
                endcase
                if (axiov == 1'b1) begin
                    $display("axiov != 0");
                end
                #20;
            end
        end
        axiiv = 1'b0;
        $display("PASSED TEST 2!");
        #400;
        // --------------------------------------------------------------------------------------------------
        // TEST 2: Off-by-one MAC Address
        // --------------------------------------------------------------------------------------------------

        // --------------------------------------------------------------------------------------------------
        // TEST 3: Another off-by-one MAC Address
        // --------------------------------------------------------------------------------------------------
        axiiv = 1'b1;
        for (int i = 47; i > 0; i = i - 8) begin
            segment = data_address3[i -: 8];
            for (int j = 7; j > 0; j = j - 2) begin
                case(j)
                    7: axiid = segment[7:6];
                    5: axiid = segment[5:4];
                    3: axiid = segment[3:2];
                    1: axiid = segment[1:0];
                    default: begin end
                endcase
                if (axiov == 1'b1) begin
                    $display("axiov != 0");
                end
                #20;
            end
        end
        for (int i = 47; i > 0; i = i - 8) begin
            segment = src_address[i -: 8];
            for (int j = 7; j > 0; j = j - 2) begin
                case(j)
                    7: axiid = segment[7:6];
                    5: axiid = segment[5:4];
                    3: axiid = segment[3:2];
                    1: axiid = segment[1:0];
                    default: begin end
                endcase
                if (axiov == 1'b1) begin
                    $display("axiov != 0");
                end
                #20;
            end
        end
        for (int i = 15; i > 0; i = i - 8) begin
            segment = len[i -: 8];
            for (int j = 7; j > 0; j = j - 2) begin
                case(j)
                    7: axiid = segment[7:6];
                    5: axiid = segment[5:4];
                    3: axiid = segment[3:2];
                    1: axiid = segment[1:0];
                    default: begin end
                endcase
                if (axiov == 1'b1) begin
                    $display("axiov != 0");
                end
                #20;
            end
        end
        for (int i = 31; i > 0; i = i - 8) begin
            segment = message[i -: 8];
            for (int j = 7; j > 0; j = j - 2) begin
                case(j)
                    7: axiid = segment[7:6];
                    5: axiid = segment[5:4];
                    3: axiid = segment[3:2];
                    1: axiid = segment[1:0];
                    default: begin end
                endcase
                if (axiov == 1'b1) begin
                    $display("axiov != 0");
                end
                #20;
            end
        end
        for (int i = 31; i > 0; i = i - 8) begin
            segment = fcs[i -: 8];
            for (int j = 7; j > 0; j = j - 2) begin
                case(j)
                    7: axiid = segment[7:6];
                    5: axiid = segment[5:4];
                    3: axiid = segment[3:2];
                    1: axiid = segment[1:0];
                    default: begin end
                endcase
                if (axiov == 1'b1) begin
                    $display("axiov != 0");
                end
                #20;
            end
        end
        axiiv = 1'b0;
        $display("PASSED TEST 3!");
        #400;
        // --------------------------------------------------------------------------------------------------
        // TEST 3: Another off-by-one MAC Address
        // --------------------------------------------------------------------------------------------------

        // --------------------------------------------------------------------------------------------------
        // TEST 4: Correct MAC Address
        // --------------------------------------------------------------------------------------------------
        axiiv = 1'b1;
        for (int i = 47; i > 0; i = i - 8) begin
            segment = data_address4[i -: 8];
            for (int j = 7; j > 0; j = j - 2) begin
                case(j)
                    7: axiid = segment[7:6];
                    5: axiid = segment[5:4];
                    3: axiid = segment[3:2];
                    1: axiid = segment[1:0];
                    default: begin end
                endcase
                if (axiov == 1'b1) begin
                    $display("axiov != 0");
                end
                #20;
            end
        end
        for (int i = 47; i > 0; i = i - 8) begin
            segment = src_address[i -: 8];
            for (int j = 7; j > 0; j = j - 2) begin
                case(j)
                    7: axiid = segment[7:6];
                    5: axiid = segment[5:4];
                    3: axiid = segment[3:2];
                    1: axiid = segment[1:0];
                    default: begin end
                endcase
                if (axiov == 1'b1) begin
                    $display("axiov != 0");
                end
                #20;
            end
        end
        for (int i = 15; i > 0; i = i - 8) begin
            segment = len[i -: 8];
            for (int j = 7; j > 0; j = j - 2) begin
                case(j)
                    7: axiid = segment[7:6];
                    5: axiid = segment[5:4];
                    3: axiid = segment[3:2];
                    1: axiid = segment[1:0];
                    default: begin end
                endcase
                #20;
                if (axiov == 1'b1) begin
                    $display("axiov != 0");
                end
            end
        end
        for (int i = 31; i > 0; i = i - 8) begin
            segment = message[i -: 8];
            for (int j = 7; j > 0; j = j - 2) begin
                case(j)
                    7: axiid = segment[7:6];
                    5: axiid = segment[5:4];
                    3: axiid = segment[3:2];
                    1: axiid = segment[1:0];
                    default: begin end
                endcase
                #20;
                if (!axiov) begin
                    $display("axiov != 1");
                end
                if (axiod != axiid) begin
                    $display("axiod is wrong");
                end
            end
        end
        for (int i = 31; i > 0; i = i - 8) begin
            segment = fcs[i -: 8];
            for (int j = 7; j > 0; j = j - 2) begin
                case(j)
                    7: axiid = segment[7:6];
                    5: axiid = segment[5:4];
                    3: axiid = segment[3:2];
                    1: axiid = segment[1:0];
                    default: begin end
                endcase
                #20;
                if (!axiov) begin
                    $display("axiov != 1");
                end
                if (axiod != axiid) begin
                    $display("axiod is wrong");
                end
            end
        end
        axiiv = 1'b0;
        $display("PASSED TEST 4!");
        #400;
        // --------------------------------------------------------------------------------------------------
        // TEST 4: Correct MAC Address
        // --------------------------------------------------------------------------------------------------

        $display("Finishing Sim");
        $finish;
    end

endmodule

`default_nettype wire

lab05/firewall.vcd
$date
	Wed Oct 26 21:03:35 2022
$end
$version
	Icarus Verilog
$end
$timescale
	1ps
$end
$scope module firewall_tb $end
$var wire 1 ! axiov $end
$var wire 2 " axiod [1:0] $end
$var reg 2 # axiid [1:0] $end
$var reg 1 $ axiiv $end
$var reg 1 % clk $end
$var reg 48 & data_address1 [47:0] $end
$var reg 48 ' data_address2 [47:0] $end
$var reg 48 ( data_address3 [47:0] $end
$var reg 48 ) data_address4 [47:0] $end
$var reg 32 * fcs [31:0] $end
$var reg 16 + len [15:0] $end
$var reg 32 , message [31:0] $end
$var reg 1 - rst $end
$var reg 8 . segment [7:0] $end
$var reg 48 / src_address [47:0] $end
$scope module my_fw $end
$var wire 2 0 axiid [1:0] $end
$var wire 1 $ axiiv $end
$var wire 1 % clk $end
$var wire 1 - rst $end
$var wire 1 ! axiov $end
$var wire 2 1 axiod [1:0] $end
$var reg 48 2 MAC_ADDRESS1 [47:0] $end
$var reg 48 3 MAC_ADDRESS2 [47:0] $end
$var reg 48 4 address [47:0] $end
$var reg 32 5 counter [31:0] $end
$var reg 1 6 flag $end
$upscope $end
$scope begin $ivl_for_loop0 $end
$var integer 32 7 i [31:0] $end
$scope begin $ivl_for_loop1 $end
$var integer 32 8 j [31:0] $end
$upscope $end
$upscope $end
$scope begin $ivl_for_loop10 $end
$var integer 32 9 i [31:0] $end
$scope begin $ivl_for_loop11 $end
$var integer 32 : j [31:0] $end
$upscope $end
$upscope $end
$scope begin $ivl_for_loop12 $end
$var integer 32 ; i [31:0] $end
$scope begin $ivl_for_loop13 $end
$var integer 32 < j [31:0] $end
$upscope $end
$upscope $end
$scope begin $ivl_for_loop14 $end
$var integer 32 = i [31:0] $end
$scope begin $ivl_for_loop15 $end
$var integer 32 > j [31:0] $end
$upscope $end
$upscope $end
$scope begin $ivl_for_loop16 $end
$var integer 32 ? i [31:0] $end
$scope begin $ivl_for_loop17 $end
$var integer 32 @ j [31:0] $end
$upscope $end
$upscope $end
$scope begin $ivl_for_loop18 $end
$var integer 32 A i [31:0] $end
$scope begin $ivl_for_loop19 $end
$var integer 32 B j [31:0] $end
$upscope $end
$upscope $end
$scope begin $ivl_for_loop2 $end
$var integer 32 C i [31:0] $end
$scope begin $ivl_for_loop3 $end
$var integer 32 D j [31:0] $end
$upscope $end
$upscope $end
$scope begin $ivl_for_loop20 $end
$var integer 32 E i [31:0] $end
$scope begin $ivl_for_loop21 $end
$var integer 32 F j [31:0] $end
$upscope $end
$upscope $end
$scope begin $ivl_for_loop22 $end
$var integer 32 G i [31:0] $end
$scope begin $ivl_for_loop23 $end
$var integer 32 H j [31:0] $end
$upscope $end
$upscope $end
$scope begin $ivl_for_loop24 $end
$var integer 32 I i [31:0] $end
$scope begin $ivl_for_loop25 $end
$var integer 32 J j [31:0] $end
$upscope $end
$upscope $end
$scope begin $ivl_for_loop26 $end
$var integer 32 K i [31:0] $end
$scope begin $ivl_for_loop27 $end
$var integer 32 L j [31:0] $end
$upscope $end
$upscope $end
$scope begin $ivl_for_loop28 $end
$var integer 32 M i [31:0] $end
$scope begin $ivl_for_loop29 $end
$var integer 32 N j [31:0] $end
$upscope $end
$upscope $end
$scope begin $ivl_for_loop30 $end
$var integer 32 O i [31:0] $end
$scope begin $ivl_for_loop31 $end
$var integer 32 P j [31:0] $end
$upscope $end
$upscope $end
$scope begin $ivl_for_loop32 $end
$var integer 32 Q i [31:0] $end
$scope begin $ivl_for_loop33 $end
$var integer 32 R j [31:0] $end
$upscope $end
$upscope $end
$scope begin $ivl_for_loop34 $end
$var integer 32 S i [31:0] $end
$scope begin $ivl_for_loop35 $end
$var integer 32 T j [31:0] $end
$upscope $end
$upscope $end
$scope begin $ivl_for_loop36 $end
$var integer 32 U i [31:0] $end
$scope begin $ivl_for_loop37 $end
$var integer 32 V j [31:0] $end
$upscope $end
$upscope $end
$scope begin $ivl_for_loop38 $end
$var integer 32 W i [31:0] $end
$scope begin $ivl_for_loop39 $end
$var integer 32 X j [31:0] $end
$upscope $end
$upscope $end
$scope begin $ivl_for_loop4 $end
$var integer 32 Y i [31:0] $end
$scope begin $ivl_for_loop5 $end
$var integer 32 Z j [31:0] $end
$upscope $end
$upscope $end
$scope begin $ivl_for_loop6 $end
$var integer 32 [ i [31:0] $end
$scope begin $ivl_for_loop7 $end
$var integer 32 \ j [31:0] $end
$upscope $end
$upscope $end
$scope begin $ivl_for_loop8 $end
$var integer 32 ] i [31:0] $end
$scope begin $ivl_for_loop9 $end
$var integer 32 ^ j [31:0] $end
$upscope $end
$upscope $end
$upscope $end
$enddefinitions $end
#0
$dumpvars
b0 ^
b0 ]
b0 \
b0 [
b0 Z
b0 Y
b0 X
b0 W
b0 V
b0 U
b0 T
b0 S
b0 R
b0 Q
b0 P
b0 O
b0 N
b0 M
b0 L
b0 K
b0 J
b0 I
b0 H
b0 G
b0 F
b0 E
b0 D
b0 C
b0 B
b0 A
b0 @
b0 ?
b0 >
b0 =
b0 <
b0 ;
b0 :
b0 9
b0 8
b0 7
x6
bx 5
b0 4
b111111111111111111111111111111111111111111111111 3
b11010010110100101011010000001100101010010010001 2
bx 1
bx 0
b111111111111111111111111111111111111111111111111 /
bx .
0-
b1001000110100 ,
b100000 +
b11001011111101000011100100100110 *
b11010010110100101011010000001100101010010010001 )
b11010010110100101011010000101100101010010010001 (
b11010010110100101011010000001100101010010010000 '
b1010011000110110000011100110100010000110100010 &
0%
x$
bx #
bx "
x!
$end
#10000
b0 "
b0 1
0!
b0 5
06
1%
#20000
0%
1-
#30000
1%
#40000
0%
0-
#50000
1%
#60000
0%
b0 #
b0 0
b111 8
b101001 .
b101111 7
1$
#70000
b1 5
1%
#80000
0%
b10 #
b10 0
b101 8
#90000
b10 4
b10 5
1%
#100000
0%
b11 8
#110000
b1010 4
b11 5
1%
#120000
0%
b1 #
b1 0
b1 8
#130000
b101001 4
b100 5
1%
#140000
0%
b10 #
b10 0
b10001101 .
b100111 7
b111 8
#150000
b10100110 4
b101 5
1%
#160000
0%
b0 #
b0 0
b101 8
#170000
b1010011000 4
b110 5
1%
#180000
0%
b11 #
b11 0
b11 8
#190000
b101001100011 4
b111 5
1%
#200000
0%
b1 #
b1 0
b1 8
#210000
b10100110001101 4
b1000 5
1%
#220000
0%
b10 #
b10 0
b10000011 .
b11111 7
b111 8
#230000
b1010011000110110 4
b1001 5
1%
#240000
0%
b0 #
b0 0
b101 8
#250000
b101001100011011000 4
b1010 5
1%
#260000
0%
b11 8
#270000
b10100110001101100000 4
b1011 5
1%
#280000
0%
b11 #
b11 0
b1 8
#290000
b1010011000110110000011 4
b1100 5
1%
#300000
0%
b10 #
b10 0
b10011010 .
b10111 7
b111 8
#310000
b101001100011011000001110 4
b1101 5
1%
#320000
0%
b1 #
b1 0
b101 8
#330000
b10100110001101100000111001 4
b1110 5
1%
#340000
0%
b10 #
b10 0
b11 8
#350000
b1010011000110110000011100110 4
b1111 5
1%
#360000
0%
b1 8
#370000
b101001100011011000001110011010 4
b10000 5
1%
#380000
0%
b0 #
b0 0
b100001 .
b1111 7
b111 8
#390000
b10100110001101100000111001101000 4
b10001 5
1%
#400000
0%
b10 #
b10 0
b101 8
#410000
b1010011000110110000011100110100010 4
b10010 5
1%
#420000
0%
b0 #
b0 0
b11 8
#430000
b101001100011011000001110011010001000 4
b10011 5
1%
#440000
0%
b1 #
b1 0
b1 8
#450000
b10100110001101100000111001101000100001 4
b10100 5
1%
#460000
0%
b10 #
b10 0
b10100010 .
b111 7
b111 8
#470000
b1010011000110110000011100110100010000110 4
b10101 5
1%
#480000
0%
b101 8
#490000
b101001100011011000001110011010001000011010 4
b10110 5
1%
#500000
0%
b0 #
b0 0
b11 8
#510000
b10100110001101100000111001101000100001101000 4
b10111 5
1%
#520000
0%
b10 #
b10 0
b1 8
#530000
b11000 5
1%
#540000
0%
b11 #
b11 0
b111 D
b11111111 .
b101111 C
b11111111111111111111111111111111 7
b11111111111111111111111111111111 8
#550000
b11001 5
1%
#560000
0%
b101 D
#570000
b11010 5
1%
#580000
0%
b11 D
#590000
b11011 5
1%
#600000
0%
b1 D
#610000
b11100 5
1%
#620000
0%
b100111 C
b111 D
#630000
b11101 5
1%
#640000
0%
b101 D
#650000
b11110 5
1%
#660000
0%
b11 D
#670000
b11111 5
1%
#680000
0%
b1 D
#690000
b100000 5
1%
#700000
0%
b11111 C
b111 D
#710000
b100001 5
1%
#720000
0%
b101 D
#730000
b100010 5
1%
#740000
0%
b11 D
#750000
b100011 5
1%
#760000
0%
b1 D
#770000
b100100 5
1%
#780000
0%
b10111 C
b111 D
#790000
b100101 5
1%
#800000
0%
b101 D
#810000
b100110 5
1%
#820000
0%
b11 D
#830000
b100111 5
1%
#840000
0%
b1 D
#850000
b101000 5
1%
#860000
0%
b1111 C
b111 D
#870000
b101001 5
1%
#880000
0%
b101 D
#890000
b101010 5
1%
#900000
0%
b11 D
#910000
b101011 5
1%
#920000
0%
b1 D
#930000
b101100 5
1%
#940000
0%
b111 C
b111 D
#950000
b101101 5
1%
#960000
0%
b101 D
#970000
b101110 5
1%
#980000
0%
b11 D
#990000
b101111 5
1%
#1000000
0%
b1 D
#1010000
b110000 5
1%
#1020000
0%
b0 #
b0 0
b111 Z
b0 .
b1111 Y
b11111111111111111111111111111111 C
b11111111111111111111111111111111 D
#1030000
b110001 5
1%
#1040000
0%
b101 Z
#1050000
b110010 5
1%
#1060000
0%
b11 Z
#1070000
b110011 5
1%
#1080000
0%
b1 Z
#1090000
b110100 5
1%
#1100000
0%
b100000 .
b111 Y
b111 Z
#1110000
b110101 5
1%
#1120000
0%
b10 #
b10 0
b101 Z
#1130000
b110110 5
1%
#1140000
0%
b0 #
b0 0
b11 Z
#1150000
b110111 5
1%
#1160000
0%
b1 Z
#1170000
b111000 5
1%
#1180000
0%
b111 \
b0 .
b11111 [
b11111111111111111111111111111111 Y
b11111111111111111111111111111111 Z
#1190000
b111001 5
1%
#1200000
0%
b101 \
#1210000
b111010 5
1%
#1220000
0%
b11 \
#1230000
b111011 5
1%
#1240000
0%
b1 \
#1250000
b111100 5
1%
#1260000
0%
b10111 [
b111 \
#1270000
b111101 5
1%
#1280000
0%
b101 \
#1290000
b111110 5
1%
#1300000
0%
b11 \
#1310000
b111111 5
1%
#1320000
0%
b1 \
#1330000
b1000000 5
1%
#1340000
0%
b10010 .
b1111 [
b111 \
#1350000
b1000001 5
1%
#1360000
0%
b1 #
b1 0
b101 \
#1370000
b1000010 5
1%
#1380000
0%
b0 #
b0 0
b11 \
#1390000
b1000011 5
1%
#1400000
0%
b10 #
b10 0
b1 \
#1410000
b1000100 5
1%
#1420000
0%
b0 #
b0 0
b110100 .
b111 [
b111 \
#1430000
b1000101 5
1%
#1440000
0%
b11 #
b11 0
b101 \
#1450000
b1000110 5
1%
#1460000
0%
b1 #
b1 0
b11 \
#1470000
b1000111 5
1%
#1480000
0%
b0 #
b0 0
b1 \
#1490000
b1001000 5
1%
#1500000
0%
b11 #
b11 0
b111 ^
b11001011 .
b11111 ]
b11111111111111111111111111111111 [
b11111111111111111111111111111111 \
#1510000
b1001001 5
1%
#1520000
0%
b0 #
b0 0
b101 ^
#1530000
b1001010 5
1%
#1540000
0%
b10 #
b10 0
b11 ^
#1550000
b1001011 5
1%
#1560000
0%
b11 #
b11 0
b1 ^
#1570000
b1001100 5
1%
#1580000
0%
b11110100 .
b10111 ]
b111 ^
#1590000
b1001101 5
1%
#1600000
0%
b101 ^
#1610000
b1001110 5
1%
#1620000
0%
b1 #
b1 0
b11 ^
#1630000
b1001111 5
1%
#1640000
0%
b0 #
b0 0
b1 ^
#1650000
b1010000 5
1%
#1660000
0%
b111001 .
b1111 ]
b111 ^
#1670000
b1010001 5
1%
#1680000
0%
b11 #
b11 0
b101 ^
#1690000
b1010010 5
1%
#1700000
0%
b10 #
b10 0
b11 ^
#1710000
b1010011 5
1%
#1720000
0%
b1 #
b1 0
b1 ^
#1730000
b1010100 5
1%
#1740000
0%
b0 #
b0 0
b100110 .
b111 ]
b111 ^
#1750000
b1010101 5
1%
#1760000
0%
b10 #
b10 0
b101 ^
#1770000
b1010110 5
1%
#1780000
0%
b1 #
b1 0
b11 ^
#1790000
b1010111 5
1%
#1800000
0%
b10 #
b10 0
b1 ^
#1810000
b1011000 5
1%
#1820000
0%
0$
b11111111111111111111111111111111 ]
b11111111111111111111111111111111 ^
#1830000
b0 5
b0 4
1%
#1840000
0%
#1850000
1%
#1860000
0%
#1870000
1%
#1880000
0%
#1890000
1%
#1900000
0%
#1910000
1%
#1920000
0%
#1930000
1%
#1940000
0%
#1950000
1%
#1960000
0%
#1970000
1%
#1980000
0%
#1990000
1%
#2000000
0%
#2010000
1%
#2020000
0%
#2030000
1%
#2040000
0%
#2050000
1%
#2060000
0%
#2070000
1%
#2080000
0%
#2090000
1%
#2100000
0%
#2110000
1%
#2120000
0%
#2130000
1%
#2140000
0%
#2150000
1%
#2160000
0%
#2170000
1%
#2180000
0%
#2190000
1%
#2200000
0%
#2210000
1%
#2220000
0%
#2230000
1%
#2240000
0%
b1 #
b1 0
b111 :
b1101001 .
b101111 9
1$
#2250000
b1 4
b1 5
1%
#2260000
0%
b10 #
b10 0
b101 :
#2270000
b110 4
b10 5
1%
#2280000
0%
b11 :
#2290000
b11010 4
b11 5
1%
#2300000
0%
b1 #
b1 0
b1 :
#2310000
b1101001 4
b100 5
1%
#2320000
0%
b100111 9
b111 :
#2330000
b110100101 4
b101 5
1%
#2340000
0%
b10 #
b10 0
b101 :
#2350000
b11010010110 4
b110 5
1%
#2360000
0%
b11 :
#2370000
b1101001011010 4
b111 5
1%
#2380000
0%
b1 #
b1 0
b1 :
#2390000
b110100101101001 4
b1000 5
1%
#2400000
0%
b1011010 .
b11111 9
b111 :
#2410000
b11010010110100101 4
b1001 5
1%
#2420000
0%
b101 :
#2430000
b1101001011010010101 4
b1010 5
1%
#2440000
0%
b10 #
b10 0
b11 :
#2450000
b110100101101001010110 4
b1011 5
1%
#2460000
0%
b1 :
#2470000
b11010010110100101011010 4
b1100 5
1%
#2480000
0%
b0 #
b0 0
b110 .
b10111 9
b111 :
#2490000
b1101001011010010101101000 4
b1101 5
1%
#2500000
0%
b101 :
#2510000
b110100101101001010110100000 4
b1110 5
1%
#2520000
0%
b1 #
b1 0
b11 :
#2530000
b11010010110100101011010000001 4
b1111 5
1%
#2540000
0%
b10 #
b10 0
b1 :
#2550000
b1101001011010010101101000000110 4
b10000 5
1%
#2560000
0%
b1 #
b1 0
b1010100 .
b1111 9
b111 :
#2570000
b110100101101001010110100000011001 4
b10001 5
1%
#2580000
0%
b101 :
#2590000
b11010010110100101011010000001100101 4
b10010 5
1%
#2600000
0%
b11 :
#2610000
b1101001011010010101101000000110010101 4
b10011 5
1%
#2620000
0%
b0 #
b0 0
b1 :
#2630000
b110100101101001010110100000011001010100 4
b10100 5
1%
#2640000
0%
b10 #
b10 0
b10010000 .
b111 9
b111 :
#2650000
b11010010110100101011010000001100101010010 4
b10101 5
1%
#2660000
0%
b1 #
b1 0
b101 :
#2670000
b1101001011010010101101000000110010101001001 4
b10110 5
1%
#2680000
0%
b0 #
b0 0
b11 :
#2690000
b110100101101001010110100000011001010100100100 4
b10111 5
1%
#2700000
0%
b1 :
#2710000
b11000 5
1%
#2720000
0%
b11 #
b11 0
b111 <
b11111111 .
b101111 ;
b11111111111111111111111111111111 9
b11111111111111111111111111111111 :
#2730000
b11001 5
1%
#2740000
0%
b101 <
#2750000
b11010 5
1%
#2760000
0%
b11 <
#2770000
b11011 5
1%
#2780000
0%
b1 <
#2790000
b11100 5
1%
#2800000
0%
b100111 ;
b111 <
#2810000
b11101 5
1%
#2820000
0%
b101 <
#2830000
b11110 5
1%
#2840000
0%
b11 <
#2850000
b11111 5
1%
#2860000
0%
b1 <
#2870000
b100000 5
1%
#2880000
0%
b11111 ;
b111 <
#2890000
b100001 5
1%
#2900000
0%
b101 <
#2910000
b100010 5
1%
#2920000
0%
b11 <
#2930000
b100011 5
1%
#2940000
0%
b1 <
#2950000
b100100 5
1%
#2960000
0%
b10111 ;
b111 <
#2970000
b100101 5
1%
#2980000
0%
b101 <
#2990000
b100110 5
1%
#3000000
0%
b11 <
#3010000
b100111 5
1%
#3020000
0%
b1 <
#3030000
b101000 5
1%
#3040000
0%
b1111 ;
b111 <
#3050000
b101001 5
1%
#3060000
0%
b101 <
#3070000
b101010 5
1%
#3080000
0%
b11 <
#3090000
b101011 5
1%
#3100000
0%
b1 <
#3110000
b101100 5
1%
#3120000
0%
b111 ;
b111 <
#3130000
b101101 5
1%
#3140000
0%
b101 <
#3150000
b101110 5
1%
#3160000
0%
b11 <
#3170000
b101111 5
1%
#3180000
0%
b1 <
#3190000
b110000 5
1%
#3200000
0%
b0 #
b0 0
b111 >
b0 .
b1111 =
b11111111111111111111111111111111 ;
b11111111111111111111111111111111 <
#3210000
b110001 5
1%
#3220000
0%
b101 >
#3230000
b110010 5
1%
#3240000
0%
b11 >
#3250000
b110011 5
1%
#3260000
0%
b1 >
#3270000
b110100 5
1%
#3280000
0%
b100000 .
b111 =
b111 >
#3290000
b110101 5
1%
#3300000
0%
b10 #
b10 0
b101 >
#3310000
b110110 5
1%
#3320000
0%
b0 #
b0 0
b11 >
#3330000
b110111 5
1%
#3340000
0%
b1 >
#3350000
b111000 5
1%
#3360000
0%
b111 @
b0 .
b11111 ?
b11111111111111111111111111111111 =
b11111111111111111111111111111111 >
#3370000
b111001 5
1%
#3380000
0%
b101 @
#3390000
b111010 5
1%
#3400000
0%
b11 @
#3410000
b111011 5
1%
#3420000
0%
b1 @
#3430000
b111100 5
1%
#3440000
0%
b10111 ?
b111 @
#3450000
b111101 5
1%
#3460000
0%
b101 @
#3470000
b111110 5
1%
#3480000
0%
b11 @
#3490000
b111111 5
1%
#3500000
0%
b1 @
#3510000
b1000000 5
1%
#3520000
0%
b10010 .
b1111 ?
b111 @
#3530000
b1000001 5
1%
#3540000
0%
b1 #
b1 0
b101 @
#3550000
b1000010 5
1%
#3560000
0%
b0 #
b0 0
b11 @
#3570000
b1000011 5
1%
#3580000
0%
b10 #
b10 0
b1 @
#3590000
b1000100 5
1%
#3600000
0%
b0 #
b0 0
b110100 .
b111 ?
b111 @
#3610000
b1000101 5
1%
#3620000
0%
b11 #
b11 0
b101 @
#3630000
b1000110 5
1%
#3640000
0%
b1 #
b1 0
b11 @
#3650000
b1000111 5
1%
#3660000
0%
b0 #
b0 0
b1 @
#3670000
b1001000 5
1%
