testing/pset7/src/crc32-mpeg.sv
/* hack to make catsoop happy ... */
`ifndef CATSOOP
`default_nettype none
`endif /* ! CATSOOP */

`timescale 1ns / 1ps

/* this module implements CRC32-MPEG2:
 *	- poly 0x04C11DB7
 *	- init 0xFFFFFFFF
 *	- no i/o reflection
 *	- no XOR out
 *
 *	== check 0x0376E6E7 ==
 */

module crc(clk, rst, axiiv, axiid, axiov, axiod);

	/* old style i/o declaration, for clarity.
	 * easier on 80-char line limits...
	 * use this if you want, we don't care - it
	 * does the same thing as the inline input/output
	 * declarations we've been using for most of the
	 * term
	 */
	input logic clk, rst;
	input logic axiiv, axiid;

	output logic axiov;
	output logic[31:0] axiod;

    logic flag;
    assign axiov = 1;

	/* your lfsr here... */
    always_ff @(posedge clk) begin
        if (rst) begin
            axiod <= 32'hFFFF_FFFF;
            flag <= 0;
        end else begin
            // x^32 + x^26 + x^23 + x^22 + x^16 + x^12 + x^11 + x^10 + x^8 + x^7 + x^5 + x^4 + x^2 + x + 1
            if (axiid) begin
                axiod[31] <= axiod[30]; 
                axiod[30] <= axiod[29]; 
                axiod[29] <= axiod[28]; 
                axiod[28] <= axiod[27];
                axiod[27] <= axiod[26]; 
                axiod[26] <= axiod[25] ^ (axiod[31] ^ axiiv); 
                axiod[25] <= axiod[24];
                axiod[24] <= axiod[23]; 
                axiod[23] <= axiod[22] ^ (axiod[31] ^ axiiv); 
                axiod[22] <= axiod[21] ^ (axiod[31] ^ axiiv);
                axiod[21] <= axiod[20]; 
                axiod[20] <= axiod[19]; 
                axiod[19] <= axiod[18]; 
                axiod[18] <= axiod[17]; 
                axiod[17] <= axiod[16];
                axiod[16] <= axiod[15] ^ (axiod[31] ^ axiiv); 
                axiod[15] <= axiod[14]; 
                axiod[14] <= axiod[13]; 
                axiod[13] <= axiod[12];
                axiod[12] <= axiod[11] ^ (axiod[31] ^ axiiv); 
                axiod[11] <= axiod[10] ^ (axiod[31] ^ axiiv); 
                axiod[10] <= axiod[9] ^ (axiod[31] ^ axiiv);
                axiod[9] <= axiod[8]; 
                axiod[8] <= axiod[7] ^ (axiod[31] ^ axiiv); 
                axiod[7] <= axiod[6] ^ (axiod[31] ^ axiiv); 
                axiod[6] <= axiod[5];
                axiod[5] <= axiod[4] ^ (axiod[31] ^ axiiv); 
                axiod[4] <= axiod[3] ^ (axiod[31] ^ axiiv); 
                axiod[3] <= axiod[2]; 
                axiod[2] <= axiod[1] ^ (axiod[31] ^ axiiv); 
                axiod[1] <= axiod[0] ^ (axiod[31] ^ axiiv); 
                axiod[0] <= axiod[31] ^ axiiv;
                flag <= 1;
            end 
            else if (flag && axiiv != 0) begin
                axiod[31] <= axiod[30]; axiod[30] <= axiod[29]; axiod[29] <= axiod[28]; axiod[28] <= axiod[27];
                axiod[27] <= axiod[26]; axiod[26] <= axiod[25] ^ (axiod[31]); axiod[25] <= axiod[24];
                axiod[24] <= axiod[23]; axiod[23] <= axiod[22] ^ (axiod[31]); axiod[22] <= axiod[21] ^ (axiod[31]);
                axiod[21] <= axiod[20]; axiod[20] <= axiod[19]; axiod[19] <= axiod[18]; axiod[18] <= axiod[17]; axiod[17] <= axiod[16];
                axiod[16] <= axiod[15] ^ (axiod[31]); axiod[15] <= axiod[14]; axiod[14] <= axiod[13]; axiod[13] <= axiod[12];
                axiod[12] <= axiod[11] ^ (axiod[31]); axiod[11] <= axiod[10] ^ (axiod[31]); axiod[10] <= axiod[9] ^ (axiod[31]);
                axiod[9] <= axiod[8]; axiod[8] <= axiod[7] ^ (axiod[31]); axiod[7] <= axiod[6] ^ (axiod[31]); axiod[6] <= axiod[5];
                axiod[5] <= axiod[4] ^ (axiod[31]); axiod[4] <= axiod[3] ^ (axiod[31]); axiod[3] <= axiod[2]; 
                axiod[2] <= axiod[1] ^ (axiod[31]); axiod[1] <= axiod[0] ^ (axiod[31]); axiod[0] <= axiod[31];
            end
        end
    end

endmodule

`ifndef CATSOOP
`default_nettype wire
`endif /* ! CATSOOP */

testing/pset7/sim/sim-mpeg.sv
/* hacks to make catsoop happy */
`ifndef CATSOOP
`default_nettype none
`endif /* ! CATSOOP */

`timescale 1ns / 1ps

/* this testbench might be slightly different than the
 * other ones you've seen before! that's because it uses
 * _macros_ - these little `define statements you see below
 *
 * macros eliminate repetition for _simple_ constants and
 * such you're interested in. it's like a parameter for
 * things you won't change and don't want to export to
 * others. to use a macro, `define it like we do below, and
 * then when you type e.g. `CP (note the backtick!) somewhere
 * `CP will get replaced with what you defined CP to.
 *
 * to run this testbench on the command line, do
 * `iverilog -g2012 -Wall -o obj/crc.out crc32-mpeg2.sv <your source file>.sv
 *
 * to run this testbench on the command line AND make a waveform, add
 * the -DMKWAVEFORM flag before the -o flag to the invocation above.
 * this will define the MKWAVEFORM macro, which allows the `ifdef
 * below in the testbench to pass. otherwise, the code in the `ifdef
 * will not be compiled into your simulation so it won't run.
 */

`define CP	10
`define HCP	(`CP / 2)

`define MSG	64'hce_2e_88_d9_b8_bc_75_de
`define CRC	32'h0d_a2_57_ed

module crcsim;

	logic clk;
	logic rst;
	logic axiiv;
	logic axiid;
	logic axiov;
	logic [31:0] axiod;

	logic [0:63] msg;
	logic [0:31] rcrc;
	logic testok;

	integer i;

	/* instantiate your uut */
	crc uut(.clk(clk), .rst(rst), .axiiv(axiiv), .axiid(axiid), .axiov(axiov), .axiod(axiod));

	/* cycle the clock forever...
	 * the CLK thing is a _label_
	 * not useful for much right now,
	 * but nice so i can quickly identify
	 * what this chunk of begin/end code does
	 */
	initial begin: CLK
		clk = 0;
		forever #`HCP clk = ~clk;
	end

	/* Another label: _MAIN_ */
	initial begin: MAIN
		/* if the MKWAVEFORM macro is defined, create a
		 * waveform and shove it into obj. otherwise, don't.
		 * this allows us control over whether a waveform
		 * gets generated without having to actually change
		 * our code, since we can force iverilog to `define
		 * MKWAVEFORM from the command line with -DMKWAVEFORM
		 * Neat!
		 *
		 * Again, don't overuse this feature! It's cool for this
		 * sort of hack, but don't overlitter your code with macros (:
	 	 */
`define MKWAVEFORM 1
`ifdef MKWAVEFORM
		$dumpfile("obj/crc32-mpeg2.vcd");
		$dumpvars(0, crcsim);
`endif /* MKWAVEFORM */

		/* spin up the test */
		testok = 1;

		/* set msg to what MSG is defined to, by writing
		 * `MSG i.e. using the macro definition we set up
		 * previously. this way we only have to change MSG
		 * at the top of the file instead of everywhere
		 * which is nice if we wanna switch up the test...
		 */
		msg = `MSG;

		/* here's an example of a code block we see
		 * run twice, but that would make a bad macro
		 * why? because what a reset is doing should be
		 * transparent to somebody reading your code. this
		 * process is unwieldly, yes, but i don't want to
		 * have to scroll to figure out what `RESET means.
		 */
		rst = 1;
		axiiv = 0;
		axiid = 0;

		#`CP;

		rst = 0;
		#`CP;

		$display("== test one: correct CRC generation ==");

		/* feed our message into the module, so that
		 * we can compute its crc and verify its integrity
		 * do this by setting valid -> 1, and shoving in
		 * message bits one at a time...
	 	 */
		for (i = 0; i < 64; i = i + 1) begin
			axiiv = 1;
			axiid = msg[i];

			/* fail the test if your module says
			 * we have invalid output at any time
			 */
			if (!axiov) testok = 0;

			/* delay by whatever CP is defined to */
			#`CP;
		end

		/* no more valid input data */
		axiid = 0;
		axiiv = 0;

		for (i = 0; i < 2; i = i + 1) begin
			/* make sure your module still has
			 * a valid output CRC in there: axiov should
			 * indicate valid data, and the data line axiod
			 * should show the correct crc
			 */
			if (!axiov) testok = 0;
			else if (axiod != `CRC) testok = 0;
			#`CP;
		end

		/* If you've got X's, fail the test! */
		if (^axiod === 1'bX) testok = 0;
		else if (^axiov === 1'bX) testok = 0;

		/* If we fail the test, jump out early */
		$display("== test one result: %s", (testok) ? "OK" : "FAIL");
		if (!testok) $finish;

		rst = 1;
		axiiv = 0;
		axiid = 0;
		#`CP;

		rst = 0;
		#`CP;

		/* Another test. Same as above. This one runs CRC over
		 * your entire message PLUS the CRC your module generates
		 * Because of magic division math, this should always produce
		 * zero !
		 */
		$display("== test two: correct residue generation ==");

		for (i = 0; i < 64; i = i + 1) begin
			axiiv = 1;
			axiid = msg[i];

			if (!axiov) testok = 0;
			#`CP;
		end
		
		rcrc = axiod;

		for (i = 0; i < 32; i = i + 1) begin
			axiiv = 1;
			axiid = rcrc[i];

			if (!axiov) testok = 0;
			#`CP;
		end

		axiid = 0;
		axiiv = 0;

		for (i = 0; i < 2; i = i + 1) begin
			if (!axiov) testok = 0;
			else if (axiod != 0) testok = 0;
			#`CP;
		end

		if (^axiod === 1'bX) testok = 0;
		else if (^axiov === 1'bX) testok = 0;

		$display("== test two result: %s", (testok) ? "OK" : "FAIL");
		$finish;
	end
endmodule

`ifndef CATSOOP
`default_nettype wire
`endif /* ! CATSOOP */

testing/pset7/obj/crc32-mpeg2.vcd
$date
	Mon Oct 03 00:51:22 2022
$end
$version
	Icarus Verilog
$end
$timescale
	1ps
$end
$scope module crcsim $end
$var wire 1 ! axiov $end
$var wire 32 " axiod [31:0] $end
$var reg 1 # axiid $end
$var reg 1 $ axiiv $end
$var reg 1 % clk $end
$var reg 64 & msg [0:63] $end
$var reg 32 ' rcrc [0:31] $end
$var reg 1 ( rst $end
$var reg 1 ) testok $end
$var integer 32 * i [31:0] $end
$scope module uut $end
$var wire 1 # axiid $end
$var wire 1 $ axiiv $end
$var wire 1 ! axiov $end
$var wire 1 % clk $end
$var wire 1 ( rst $end
$var reg 32 + axiod [31:0] $end
$var reg 1 , flag $end
$upscope $end
$scope begin CLK $end
$upscope $end
$scope begin MAIN $end
$upscope $end
$upscope $end
$enddefinitions $end
#0
$dumpvars
x,
bx +
bx *
1)
1(
bx '
b1100111000101110100010001101100110111000101111000111010111011110 &
0%
0$
0#
bx "
1!
$end
#5000
0,
b11111111111111111111111111111111 "
b11111111111111111111111111111111 +
1%
#10000
0%
0(
#15000
1%
#20000
0%
1#
1$
b0 *
#25000
1,
b11111111111111111111111111111110 "
b11111111111111111111111111111110 +
1%
#30000
0%
b1 *
#35000
b11111111111111111111111111111100 "
b11111111111111111111111111111100 +
1%
#40000
0%
0#
b10 *
#45000
b11111011001111101110001001001111 "
b11111011001111101110001001001111 +
1%
#50000
0%
b11 *
#55000
b11110010101111001101100100101001 "
b11110010101111001101100100101001 +
1%
#60000
0%
1#
b100 *
#65000
b11100101011110011011001001010010 "
b11100101011110011011001001010010 +
1%
#70000
0%
b101 *
#75000
b11001010111100110110010010100100 "
b11001010111100110110010010100100 +
1%
#80000
0%
b110 *
#85000
b10010101111001101100100101001000 "
b10010101111001101100100101001000 +
1%
#90000
0%
0#
b111 *
#95000
b101111000011001000111100100111 "
b101111000011001000111100100111 +
1%
#100000
0%
b1000 *
#105000
b1011110000110010001111001001110 "
b1011110000110010001111001001110 +
1%
#110000
0%
b1001 *
#115000
b10111100001100100011110010011100 "
b10111100001100100011110010011100 +
1%
#120000
0%
1#
b1010 *
#125000
b1111000011001000111100100111000 "
b1111000011001000111100100111000 +
1%
#130000
0%
0#
b1011 *
#135000
b11110000110010001111001001110000 "
b11110000110010001111001001110000 +
1%
#140000
0%
1#
b1100 *
#145000
b11100001100100011110010011100000 "
b11100001100100011110010011100000 +
1%
#150000
0%
b1101 *
#155000
b11000011001000111100100111000000 "
b11000011001000111100100111000000 +
1%
#160000
0%
b1110 *
#165000
b10000110010001111001001110000000 "
b10000110010001111001001110000000 +
1%
#170000
0%
0#
b1111 *
#175000
b1000010011100011101010110111 "
b1000010011100011101010110111 +
1%
#180000
0%
1#
b10000 *
#185000
b10100010111010110100011011001 "
b10100010111010110100011011001 +
1%
#190000
0%
0#
b10001 *
#195000
b101000101110101101000110110010 "
b101000101110101101000110110010 +
1%
#200000
0%
b10010 *
#205000
b1010001011101011010001101100100 "
b1010001011101011010001101100100 +
1%
#210000
0%
b10011 *
#215000
b10100010111010110100011011001000 "
b10100010111010110100011011001000 +
1%
#220000
0%
1#
b10100 *
#225000
b1000101110101101000110110010000 "
b1000101110101101000110110010000 +
1%
#230000
0%
0#
b10101 *
#235000
b10001011101011010001101100100000 "
b10001011101011010001101100100000 +
1%
#240000
0%
b10110 *
#245000
b10011100110110010101111110111 "
b10011100110110010101111110111 +
1%
#250000
0%
b10111 *
#255000
b100111001101100101011111101110 "
b100111001101100101011111101110 +
1%
#260000
0%
1#
b11000 *
#265000
b1001010101011011011001001101011 "
b1001010101011011011001001101011 +
1%
#270000
0%
b11001 *
#275000
b10010001100110100111100101100001 "
b10010001100110100111100101100001 +
1%
#280000
0%
0#
b11010 *
#285000
b100111111101011110111101110101 "
b100111111101011110111101110101 +
1%
#290000
0%
1#
b11011 *
#295000
b1001011001010101100001101011101 "
b1001011001010101100001101011101 +
1%
#300000
0%
b11100 *
#305000
b10010010100101001001101100001101 "
b10010010100101001001101100001101 +
1%
#310000
0%
0#
b11101 *
#315000
b100001111010000010101110101101 "
b100001111010000010101110101101 +
1%
#320000
0%
b11110 *
#325000
b1000011110100000101011101011010 "
b1000011110100000101011101011010 +
1%
#330000
0%
1#
b11111 *
#335000
b10000011011000011011001100000011 "
b10000011011000011011001100000011 +
1%
#340000
0%
b100000 *
#345000
b110110000110110011000000110 "
b110110000110110011000000110 +
1%
#350000
0%
0#
b100001 *
#355000
b1101100001101100110000001100 "
b1101100001101100110000001100 +
1%
#360000
0%
1#
b100010 *
#365000
b11111110011001000010110101111 "
b11111110011001000010110101111 +
1%
#370000
0%
b100011 *
#375000
b111011010110000001011011101001 "
b111011010110000001011011101001 +
1%
#380000
0%
b100100 *
#385000
b1110010011100010011000001100101 "
b1110010011100010011000001100101 +
1%
#390000
0%
0#
b100101 *
#395000
b11100100111000100110000011001010 "
b11100100111000100110000011001010 +
1%
#400000
0%
b100110 *
#405000
b11001101000001011101110000100011 "
b11001101000001011101110000100011 +
1%
#410000
0%
b100111 *
#415000
b10011110110010101010010111110001 "
b10011110110010101010010111110001 +
1%
#420000
0%
1#
b101000 *
#425000
b111101100101010100101111100010 "
b111101100101010100101111100010 +
1%
#430000
0%
0#
b101001 *
#435000
b1111011001010101001011111000100 "
b1111011001010101001011111000100 +
1%
#440000
0%
1#
b101010 *
#445000
b11110010100101000011001000111111 "
b11110010100101000011001000111111 +
1%
#450000
0%
b101011 *
#455000
b11100101001010000110010001111110 "
b11100101001010000110010001111110 +
1%
#460000
0%
b101100 *
#465000
b11001010010100001100100011111100 "
b11001010010100001100100011111100 +
1%
#470000
0%
b101101 *
#475000
b10010100101000011001000111111000 "
b10010100101000011001000111111000 +
1%
#480000
0%
0#
b101110 *
#485000
b101101100000100011111001000111 "
b101101100000100011111001000111 +
1%
#490000
0%
b101111 *
#495000
b1011011000001000111110010001110 "
b1011011000001000111110010001110 +
1%
#500000
0%
b110000 *
#505000
b10110110000010001111100100011100 "
b10110110000010001111100100011100 +
1%
#510000
0%
1#
b110001 *
#515000
b1101100000100011111001000111000 "
b1101100000100011111001000111000 +
1%
#520000
0%
b110010 *
#525000
b11011100111000101111100111000111 "
b11011100111000101111100111000111 +
1%
#530000
0%
b110011 *
#535000
b10111001110001011111001110001110 "
b10111001110001011111001110001110 +
1%
#540000
0%
0#
b110100 *
#545000
b1110111010010101111101010101011 "
b1110111010010101111101010101011 +
1%
#550000
0%
1#
b110101 *
#555000
b11101010010101001110100011100001 "
b11101010010101001110100011100001 +
1%
#560000
0%
0#
b110110 *
#565000
b11010000011010001100110001110101 "
b11010000011010001100110001110101 +
1%
#570000
0%
1#
b110111 *
#575000
b10100000110100011001100011101010 "
b10100000110100011001100011101010 +
1%
#580000
0%
b111000 *
#585000
b1000001101000110011000111010100 "
b1000001101000110011000111010100 +
1%
#590000
0%
b111001 *
#595000
b10000111100001110111111000011111 "
b10000111100001110111111000011111 +
1%
#600000
0%
0#
b111010 *
#605000
b1011110011111110000110001001 "
b1011110011111110000110001001 +
1%
#610000
0%
1#
b111011 *
#615000
b10011010111101101111010100101 "
b10011010111101101111010100101 +
1%
#620000
0%
b111100 *
#625000
b100010011111001010000011111101 "
b100010011111001010000011111101 +
1%
#630000
0%
b111101 *
#635000
b1000000001110000101110001001101 "
b1000000001110000101110001001101 +
1%
#640000
0%
b111110 *
#645000
b10000100101100011010010100101101 "
b10000100101100011010010100101101 +
1%
#650000
0%
0#
b111111 *
#655000
b1101101000100101011111101101 "
b1101101000100101011111101101 +
1%
#660000
0%
0$
b0 *
#665000
1%
#670000
0%
b1 *
#675000
1%
#680000
0%
1(
b10 *
#685000
0,
b11111111111111111111111111111111 "
b11111111111111111111111111111111 +
1%
#690000
0%
0(
#695000
1%
#700000
0%
1#
1$
b0 *
#705000
1,
b11111111111111111111111111111110 "
b11111111111111111111111111111110 +
1%
#710000
0%
b1 *
#715000
b11111111111111111111111111111100 "
b11111111111111111111111111111100 +
1%
#720000
0%
0#
b10 *
#725000
b11111011001111101110001001001111 "
b11111011001111101110001001001111 +
1%
#730000
0%
b11 *
#735000
b11110010101111001101100100101001 "
b11110010101111001101100100101001 +
1%
#740000
0%
1#
b100 *
#745000
b11100101011110011011001001010010 "
b11100101011110011011001001010010 +
1%
#750000
0%
b101 *
#755000
b11001010111100110110010010100100 "
b11001010111100110110010010100100 +
1%
#760000
0%
b110 *
#765000
b10010101111001101100100101001000 "
b10010101111001101100100101001000 +
1%
#770000
0%
0#
b111 *
#775000
b101111000011001000111100100111 "
b101111000011001000111100100111 +
1%
#780000
0%
b1000 *
#785000
b1011110000110010001111001001110 "
b1011110000110010001111001001110 +
1%
#790000
0%
b1001 *
#795000
b10111100001100100011110010011100 "
b10111100001100100011110010011100 +
1%
#800000
0%
1#
b1010 *
#805000
b1111000011001000111100100111000 "
b1111000011001000111100100111000 +
1%
#810000
0%
0#
b1011 *
#815000
b11110000110010001111001001110000 "
b11110000110010001111001001110000 +
1%
#820000
0%
1#
b1100 *
#825000
b11100001100100011110010011100000 "
b11100001100100011110010011100000 +
1%
#830000
0%
b1101 *
#835000
b11000011001000111100100111000000 "
b11000011001000111100100111000000 +
1%
#840000
0%
b1110 *
#845000
b10000110010001111001001110000000 "
b10000110010001111001001110000000 +
1%
#850000
0%
0#
b1111 *
#855000
b1000010011100011101010110111 "
b1000010011100011101010110111 +
1%
#860000
0%
1#
b10000 *
#865000
b10100010111010110100011011001 "
b10100010111010110100011011001 +
1%
#870000
0%
0#
b10001 *
#875000
b101000101110101101000110110010 "
b101000101110101101000110110010 +
1%
#880000
0%
b10010 *
#885000
b1010001011101011010001101100100 "
b1010001011101011010001101100100 +
1%
#890000
0%
b10011 *
#895000
b10100010111010110100011011001000 "
b10100010111010110100011011001000 +
1%
#900000
0%
1#
b10100 *
#905000
b1000101110101101000110110010000 "
b1000101110101101000110110010000 +
1%
#910000
0%
0#
b10101 *
#915000
b10001011101011010001101100100000 "
b10001011101011010001101100100000 +
1%
#920000
0%
b10110 *
#925000
b10011100110110010101111110111 "
b10011100110110010101111110111 +
1%
#930000
0%
b10111 *
#935000
b100111001101100101011111101110 "
b100111001101100101011111101110 +
1%
#940000
0%
1#
b11000 *
#945000
b1001010101011011011001001101011 "
b1001010101011011011001001101011 +
1%
#950000
0%
b11001 *
#955000
b10010001100110100111100101100001 "
b10010001100110100111100101100001 +
1%
#960000
0%
0#
b11010 *
#965000
b100111111101011110111101110101 "
b100111111101011110111101110101 +
1%
#970000
0%
1#
b11011 *
#975000
b1001011001010101100001101011101 "
b1001011001010101100001101011101 +
1%
#980000
0%
b11100 *
#985000
b10010010100101001001101100001101 "
b10010010100101001001101100001101 +
1%
#990000
0%
0#
b11101 *
#995000
b100001111010000010101110101101 "
b100001111010000010101110101101 +
1%
#1000000
0%
b11110 *
#1005000
b1000011110100000101011101011010 "
b1000011110100000101011101011010 +
1%
#1010000
0%
1#
b11111 *
#1015000
b10000011011000011011001100000011 "
b10000011011000011011001100000011 +
1%
#1020000
0%
b100000 *
#1025000
b110110000110110011000000110 "
b110110000110110011000000110 +
1%
#1030000
0%
0#
b100001 *
#1035000
b1101100001101100110000001100 "
b1101100001101100110000001100 +
1%
#1040000
0%
1#
b100010 *
#1045000
b11111110011001000010110101111 "
b11111110011001000010110101111 +
1%
#1050000
0%
b100011 *
#1055000
b111011010110000001011011101001 "
b111011010110000001011011101001 +
1%
#1060000
0%
b100100 *
#1065000
b1110010011100010011000001100101 "
b1110010011100010011000001100101 +
1%
#1070000
0%
0#
b100101 *
#1075000
b11100100111000100110000011001010 "
b11100100111000100110000011001010 +
1%
#1080000
0%
b100110 *
#1085000
b11001101000001011101110000100011 "
b11001101000001011101110000100011 +
1%
#1090000
0%
b100111 *
#1095000
b10011110110010101010010111110001 "
b10011110110010101010010111110001 +
1%
#1100000
0%
1#
b101000 *
#1105000
b111101100101010100101111100010 "
b111101100101010100101111100010 +
1%
#1110000
0%
0#
b101001 *
#1115000
b1111011001010101001011111000100 "
b1111011001010101001011111000100 +
1%
#1120000
0%
1#
b101010 *
#1125000
b11110010100101000011001000111111 "
b11110010100101000011001000111111 +
1%
#1130000
0%
b101011 *
#1135000
b11100101001010000110010001111110 "
b11100101001010000110010001111110 +
1%
#1140000
0%
b101100 *
#1145000
b11001010010100001100100011111100 "
b11001010010100001100100011111100 +
1%
#1150000
0%
b101101 *
#1155000
b10010100101000011001000111111000 "
b10010100101000011001000111111000 +
1%
#1160000
0%
0#
b101110 *
#1165000
b101101100000100011111001000111 "
b101101100000100011111001000111 +
1%
#1170000
0%
b101111 *
#1175000
b1011011000001000111110010001110 "
b1011011000001000111110010001110 +
1%
#1180000
0%
b110000 *
#1185000
b10110110000010001111100100011100 "
b10110110000010001111100100011100 +
1%
#1190000
0%
1#
b110001 *
#1195000
b1101100000100011111001000111000 "
b1101100000100011111001000111000 +
1%
#1200000
0%
b110010 *
#1205000
b11011100111000101111100111000111 "
b11011100111000101111100111000111 +
1%
#1210000
0%
b110011 *
#1215000
b10111001110001011111001110001110 "
b10111001110001011111001110001110 +
1%
#1220000
0%
0#
b110100 *
#1225000
b1110111010010101111101010101011 "
b1110111010010101111101010101011 +
1%
#1230000
0%
1#
b110101 *
#1235000
b11101010010101001110100011100001 "
b11101010010101001110100011100001 +
1%
#1240000
0%
0#
b110110 *
#1245000
b11010000011010001100110001110101 "
b11010000011010001100110001110101 +
1%
#1250000
0%
1#
b110111 *
#1255000
b10100000110100011001100011101010 "
b10100000110100011001100011101010 +
1%
#1260000
0%
b111000 *
#1265000
b1000001101000110011000111010100 "
b1000001101000110011000111010100 +
1%
#1270000
0%
b111001 *
#1275000
b10000111100001110111111000011111 "
b10000111100001110111111000011111 +
1%
#1280000
0%
0#
b111010 *
#1285000
b1011110011111110000110001001 "
b1011110011111110000110001001 +
1%
#1290000
0%
1#
b111011 *
#1295000
b10011010111101101111010100101 "
b10011010111101101111010100101 +
1%
#1300000
0%
b111100 *
#1305000
b100010011111001010000011111101 "
b100010011111001010000011111101 +
1%
#1310000
0%
b111101 *
#1315000
b1000000001110000101110001001101 "
b1000000001110000101110001001101 +
1%
#1320000
0%
b111110 *
#1325000
b10000100101100011010010100101101 "
b10000100101100011010010100101101 +
1%
#1330000
0%
0#
b111111 *
#1335000
b1101101000100101011111101101 "
b1101101000100101011111101101 +
1%
#1340000
0%
b1101101000100101011111101101 '
b0 *
#1345000
b11011010001001010111111011010 "
b11011010001001010111111011010 +
1%
#1350000
0%
b1 *
#1355000
b110110100010010101111110110100 "
b110110100010010101111110110100 +
1%
#1360000
0%
b10 *
#1365000
b1101101000100101011111101101000 "
b1101101000100101011111101101000 +
1%
#1370000
0%
b11 *
#1375000
b11011010001001010111111011010000 "
b11011010001001010111111011010000 +
1%
#1380000
0%
1#
b100 *
#1385000
b10110100010010101111110110100000 "
b10110100010010101111110110100000 +
1%
#1390000
0%
b101 *
#1395000
b1101000100101011111101101000000 "
b1101000100101011111101101000000 +
1%
#1400000
0%
0#
b110 *
#1405000
b11010001001010111111011010000000 "
b11010001001010111111011010000000 +
1%
#1410000
0%
1#
b111 *
#1415000
b10100010010101111110110100000000 "
b10100010010101111110110100000000 +
1%
#1420000
0%
b1000 *
#1425000
b1000100101011111101101000000000 "
b1000100101011111101101000000000 +
1%
#1430000
0%
0#
b1001 *
#1435000
b10001001010111111011010000000000 "
b10001001010111111011010000000000 +
1%
#1440000
0%
1#
b1010 *
#1445000
b10010101111110110100000000000 "
b10010101111110110100000000000 +
1%
#1450000
0%
0#
b1011 *
#1455000
b100101011111101101000000000000 "
b100101011111101101000000000000 +
1%
#1460000
0%
b1100 *
#1465000
b1001010111111011010000000000000 "
b1001010111111011010000000000000 +
1%
#1470000
0%
b1101 *
#1475000
b10010101111110110100000000000000 "
b10010101111110110100000000000000 +
1%
#1480000
0%
1#
b1110 *
#1485000
b101011111101101000000000000000 "
b101011111101101000000000000000 +
1%
#1490000
0%
0#
b1111 *
#1495000
b1010111111011010000000000000000 "
b1010111111011010000000000000000 +
1%
#1500000
0%
b10000 *
#1505000
b10101111110110100000000000000000 "
b10101111110110100000000000000000 +
1%
#1510000
0%
1#
b10001 *
#1515000
b1011111101101000000000000000000 "
b1011111101101000000000000000000 +
1%
#1520000
0%
0#
b10010 *
#1525000
b10111111011010000000000000000000 "
b10111111011010000000000000000000 +
1%
#1530000
0%
1#
b10011 *
#1535000
b1111110110100000000000000000000 "
b1111110110100000000000000000000 +
1%
#1540000
0%
0#
b10100 *
#1545000
b11111101101000000000000000000000 "
b11111101101000000000000000000000 +
1%
#1550000
0%
1#
b10101 *
#1555000
b11111011010000000000000000000000 "
b11111011010000000000000000000000 +
1%
#1560000
0%
b10110 *
#1565000
b11110110100000000000000000000000 "
b11110110100000000000000000000000 +
1%
#1570000
0%
b10111 *
#1575000
b11101101000000000000000000000000 "
b11101101000000000000000000000000 +
1%
#1580000
0%
b11000 *
#1585000
b11011010000000000000000000000000 "
b11011010000000000000000000000000 +
1%
#1590000
0%
b11001 *
#1595000
b10110100000000000000000000000000 "
b10110100000000000000000000000000 +
1%
#1600000
0%
b11010 *
#1605000
b1101000000000000000000000000000 "
b1101000000000000000000000000000 +
1%
#1610000
0%
0#
b11011 *
#1615000
b11010000000000000000000000000000 "
b11010000000000000000000000000000 +
1%
#1620000
0%
1#
b11100 *
#1625000
b10100000000000000000000000000000 "
b10100000000000000000000000000000 +
1%
#1630000
0%
b11101 *
#1635000
b1000000000000000000000000000000 "
b1000000000000000000000000000000 +
1%
#1640000
0%
0#
b11110 *
#1645000
b10000000000000000000000000000000 "
b10000000000000000000000000000000 +
1%
#1650000
0%
1#
b11111 *
#1655000
b0 "
b0 +
1%
#1660000
0%
0$
0#
b0 *
#1665000
1%
#1670000
0%
b1 *
#1675000
1%
#1680000
0%
b10 *
