testing/pset7/src/crc32-bzip2.sv
`ifndef CATSOOP
`default_nettype none
`endif /* ! CATSOOP */

`timescale 1ns / 1ps

/* TODO: read this module and then have it bitwise-complement
 * its output, without borking the CRC32 calculation happening
 * on the inside.
 */

/* this is a verilog pre-processor macro. you'll start to
 * see more of these as the labs go on. these basically cut
 * and paste across your code - for example, anywhere I type
 * `LAGGING_TAPS (watch the backtick there in front of it!),
 * that's gonna get replaced with 4, 7, 10, 16, 22, 26 word for
 * word in your source code.
 *
 * Use these carefully! don't create macros that are unintuitive
 * or difficult to understand - use them to nuke off repetition
 * of constants throughout your code.
 */
`define LAGGING_TAPS 4, 7, 10, 16, 22, 26
`define DOUBLED_TAPS 2, 5, 8, 11, 12, 23
`define LEADING_TAPS 3, 6, 9, 13, 17, 24, 27

/* You don't have to worry about how this works too much.
 * If you're curious, draw out the circuit and convince
 * yourself it's functionally equivalent to the one-bit-
 * at-a-time version. We have to do some extra math to
 * compensate that we've now got multiple bits at each
 * 'slot' in the LFSR...defining stuff in macros makes
 * it a bit easier to comprehend.
 */
`define LAGGING_SHIFT_IN (taxiod[30] ^ axiid[0])
`define LEADING_SHIFT_IN (taxiod[31] ^ axiid[1])
`define DOUBLED_SHIFT_IN (`LEADING_SHIFT_IN ^ `LAGGING_SHIFT_IN)


/* this module [should] implement CRC32-BZIP2, with a two bit input:
 *	- poly 0x04C11DB7
 *	- init 0xFFFFFFFF
 *	- NEW: XOR outputs
 *
 *	== check: 0xfc891918 ==
 *
 * this will be the ethernet checksum when you're done!
 */

module crc(clk, rst, axiiv, axiid, axiov, axiod);

	/* old style i/o declaration, for clarity.
	 * easier on 80-char line limits...
	 * use this if you want, we don't care
	 */
	input logic clk, rst;

	input logic axiiv;
	input logic[1:0] axiid;

	output logic axiov;
	output logic[31:0] axiod;

	logic[31:0] saxiod;
    logic[31:0] taxiod;
	integer i;
    logic flag;

	/* our outputs are always valid */
	assign axiov = 1;

	always_comb begin
		/* for every register in the lfsr, implement
		 * the schematic (giant case statement gets
		 * much smaller with macros, tastefully applied)
		 *
		 * this for loop is similar to the LFSRs you've
		 * seen before - it's just two bits at a time, so
	 	 * some of the math is screwed with a bit.
		 *
		 * you'll notice the cases are sometimes macros -
		 * defined as constant lists of numbers. you can
		 * have multiple numbers per 'arm' of the case
		 * statement - this serves to make things shorter!
		 */
		for (i = 0; i < 32; i = i + 1) begin
			case (i)
			0: saxiod[i] = `LAGGING_SHIFT_IN;
			1: saxiod[i] = `DOUBLED_SHIFT_IN;

			`LAGGING_TAPS:
				saxiod[i] = taxiod[i - 2] ^ `LAGGING_SHIFT_IN;
			`DOUBLED_TAPS:
				saxiod[i] = taxiod[i - 2] ^ `DOUBLED_SHIFT_IN;
			`LEADING_TAPS:
				saxiod[i] = taxiod[i - 2] ^ `LEADING_SHIFT_IN;

			default: saxiod[i] = taxiod[i - 2];
			endcase
		end
	end

    assign axiod = taxiod ^ 32'hFFFF_FFFF;
	always_ff @(posedge clk) begin
		/* init 0xFFFFFFFF */
		if (rst) begin
            taxiod <= 32'hFFFF_FFFF;
        end 
		/* our output validity hinges on whether
		 * we are calculating anything or not
		 * on this clock cycle. if there is no
		 * valid input for us, don't do a shift
	 	 * this cycle
		 */
		else taxiod <= (axiiv) ? saxiod : taxiod;
	end

endmodule

`ifndef CATSOOP
`default_nettype wire
`endif /* ! CATSOOP */

testing/pset7/sim/sim-bzip2.sv
/* hack to make catsoop happy */

`ifndef CATSOOP
`default_nettype none
`endif /* ! CATSOOP */

`timescale 1ns / 1ps

`define CP	10
`define HCP	(`CP / 2)

`define MSG	64'h67_69_60_d1_9d_78_5a_5b
`define CRC	32'h96_cb_5e_37

/* the result of the crc32-bzip2 is
 * post-complemented during transmission.
 * as a result, we'll no longer end up with
 * a zero result when we shift the crc32 into
 * our LFSR. instead, we get this non-zero
 * magic value which should be consistent
 * across sends
 */
`define MAGIC_CHECK 32'h38_fb_22_84

module crcsim;

	logic clk;
	logic rst;
	logic axiiv;
	logic [1:0] axiid;
	logic axiov;
	logic [31:0] axiod;

	logic [0:63] msg;
	logic [0:31] rcrc;
	logic testok;

	integer i;

	crc uut(.clk(clk), .rst(rst), .axiiv(axiiv), .axiid(axiid), .axiov(axiov), .axiod(axiod));

	initial begin: CLK
		clk = 0;
		forever #`HCP clk = ~clk;
	end

	initial begin: MAIN
`define MKWAVEFORM 1;
`ifdef MKWAVEFORM
		$dumpfile("obj/crc32-bzip2-dp.vcd");
		$dumpvars(0, crcsim);
`endif /* MKWAVEFORM */

		/* spin up the lfsr */
		testok = 1;
		msg = `MSG;

		rst = 1;
		axiiv = 0;
		axiid = 0;
		#`CP;

		rst = 0;
		#`CP;

		$display("== test one: correct CRC generation ==");

		for (i = 0; i < 64; i = i + 2) begin
			axiiv = 1;
			axiid = {msg[i], msg[i+1]};

			if (!axiov) testok = 0;
			#`CP;
		end

		axiid = 0;
		axiiv = 0;

		for (i = 0; i < 2; i = i + 1) begin
			if (!axiov) testok = 0;
			else if (axiod != `CRC) testok = 0;
			#`CP;
		end

		if (^axiod === 1'bX) testok = 0;
		else if (^axiov === 1'bX) testok = 0;

		$display("== test one result: %s", (testok) ? "OK" : "FAIL");
		if (!testok) $finish;

		rst = 1;
		axiiv = 0;
		axiid = 0;
		#`CP;

		rst = 0;
		#`CP;

		$display("== test two: correct residue generation ==");

		for (i = 0; i < 64; i = i + 2) begin
			axiiv = 1;
			axiid = {msg[i], msg[i+1]};

			if (!axiov) testok = 0;
			#`CP;
		end
		
		rcrc = axiod;

		for (i = 0; i < 32; i = i + 2) begin
			axiiv = 1;
			axiid = {rcrc[i], rcrc[i+1]};

			if (!axiov) testok = 0;
			#`CP;
		end

		axiid = 0;
		axiiv = 0;

		for (i = 0; i < 2; i = i + 1) begin
			if (!axiov) testok = 0;
			else if (axiod != `MAGIC_CHECK) testok = 0;
			#`CP;
		end

		if (^axiod === 1'bX) testok = 0;
		else if (^axiov === 1'bX) testok = 0;

		$display("== test two result: %s", (testok) ? "OK" : "FAIL");
		$finish;
	end
endmodule

`ifndef CATSOOP
`default_nettype wire
`endif /* ! CATSOOP */

testing/pset7/obj/crc32-bzip2-dp.vcd
$date
	Mon Oct 03 01:51:55 2022
$end
$version
	Icarus Verilog
$end
$timescale
	1ps
$end
$scope module crcsim $end
$var wire 1 ! axiov $end
$var wire 32 " axiod [31:0] $end
$var reg 2 # axiid [1:0] $end
$var reg 1 $ axiiv $end
$var reg 1 % clk $end
$var reg 64 & msg [0:63] $end
$var reg 32 ' rcrc [0:31] $end
$var reg 1 ( rst $end
$var reg 1 ) testok $end
$var integer 32 * i [31:0] $end
$scope module uut $end
$var wire 2 + axiid [1:0] $end
$var wire 1 $ axiiv $end
$var wire 32 , axiod [31:0] $end
$var wire 1 ! axiov $end
$var wire 1 % clk $end
$var wire 1 ( rst $end
$var reg 32 - saxiod [31:0] $end
$var reg 32 . taxiod [31:0] $end
$var integer 32 / i [31:0] $end
$upscope $end
$scope begin CLK $end
$upscope $end
$scope begin MAIN $end
$upscope $end
$upscope $end
$enddefinitions $end
#0
$dumpvars
b100000 /
bx .
bx -
bx ,
b0 +
bx *
1)
1(
bx '
b110011101101001011000001101000110011101011110000101101001011011 &
0%
0$
b0 #
bx "
1!
$end
#5000
b11110010101111001101100100100101 -
b100000 /
b0 "
b0 ,
b11111111111111111111111111111111 .
1%
#10000
0%
0(
#15000
1%
#20000
b11110110011111011100010010010010 -
b100000 /
0%
b1 #
b1 +
1$
b0 *
#25000
b11010000011101010010100100100110 -
b100000 /
b1001100000100011101101101101 "
b1001100000100011101101101101 ,
b11110110011111011100010010010010 .
1%
#30000
b11011101001101100000111111111111 -
b100000 /
0%
b10 #
b10 +
b10 *
#35000
b1110000000110010010001001001011 -
b100000 /
b100010110010011111000000000000 "
b100010110010011111000000000000 ,
b11011101001101100000111111111111 .
1%
#40000
b1111101010110100000010010010010 -
b100000 /
0%
b1 #
b1 +
b100 *
#45000
b11110101011010000001001001001000 -
b100000 /
b10000010101001011111101101101101 "
b10000010101001011111101101101101 ,
b1111101010110100000010010010010 .
1%
#50000
b11111100111010100010100100100110 -
b100000 /
0%
b11 #
b11 +
b110 *
#55000
b11110011101010001010010010011000 -
b100000 /
b11000101011101011011011001 "
b11000101011101011011011001 ,
b11111100111010100010100100100110 .
1%
#60000
b11111010001010101001111111110110 -
b100000 /
0%
b1 #
b1 +
b1000 *
#65000
b11100001001010000100010010110110 -
b100000 /
b101110101010110000000001001 "
b101110101010110000000001001 ,
b11111010001010101001111111110110 .
1%
#70000
b11101100011010110110001001101111 -
b100000 /
0%
b10 #
b10 +
b1010 *
#75000
b10110101011011001001010000001011 -
b100000 /
b10011100101001001110110010000 "
b10011100101001001110110010000 ,
b11101100011010110110001001101111 .
1%
#80000
0%
b1100 *
#85000
b11010101101100100101000000101100 -
b100000 /
b1001010100100110110101111110100 "
b1001010100100110110101111110100 ,
b10110101011011001001010000001011 .
1%
#90000
b11011000111100010111011011110101 -
b100000 /
0%
b1 #
b1 +
b1110 *
#95000
b1101010010001111110000010111010 -
b100000 /
b100111000011101000100100001010 "
b100111000011101000100100001010 ,
b11011000111100010111011011110101 .
1%
#100000
0%
b10000 *
#105000
b10101001000111111000001011101000 -
b100000 /
b10010101101110000001111101000101 "
b10010101101110000001111101000101 ,
b1101010010001111110000010111010 .
1%
#110000
b10100100010111001010010000110001 -
b100000 /
0%
b10 #
b10 +
b10010 *
#115000
b10010001011100101001000011000100 -
b100000 /
b1011011101000110101101111001110 "
b1011011101000110101101111001110 ,
b10100100010111001010010000110001 .
1%
#120000
b10011000111100001010101110101010 -
b100000 /
0%
b0 #
b0 +
b10100 *
#125000
b1101010010000001001010111000110 -
b100000 /
b1100111000011110101010001010101 "
b1100111000011110101010001010101 ,
b10011000111100001010101110101010 .
1%
#130000
0%
b10110 *
#135000
b10101101110000110100101010101111 -
b100000 /
b10010101101111110110101000111001 "
b10010101101111110110101000111001 ,
b1101010010000001001010111000110 .
1%
#140000
b10100000100000000110110001110110 -
b100000 /
0%
b11 #
b11 +
b11000 *
#145000
b10000110110000001010110001101111 -
b100000 /
b1011111011111111001001110001001 "
b1011111011111111001001110001001 ,
b10100000100000000110110001110110 .
1%
#150000
b10001111010000101001011100000001 -
b100000 /
0%
b1 #
b1 +
b11010 *
#155000
b110000010010010111101011011101 -
b100000 /
b1110000101111010110100011111110 "
b1110000101111010110100011111110 ,
b10001111010000101001011100000001 .
1%
#160000
b110100100010000110011101101010 -
b100000 /
0%
b0 #
b0 +
b11100 *
#165000
b11010010001000011001110110101000 -
b100000 /
b11001011011101111001100010010101 "
b11001011011101111001100010010101 ,
b110100100010000110011101101010 .
1%
#170000
b11010110111000001000000000011111 -
b100000 /
0%
b1 #
b1 +
b11110 *
#175000
b1010010000000000011101100010010 -
b100000 /
b101001000111110111111111100000 "
b101001000111110111111111100000 ,
b11010110111000001000000000011111 .
1%
#180000
b1011111010000110001110111001011 -
b100000 /
0%
b10 #
b10 +
b100000 *
#185000
b1110000010011110101000111110101 -
b100000 /
b10100000101111001110001000110100 "
b10100000101111001110001000110100 ,
b1011111010000110001110111001011 .
1%
#190000
b1111101000011000111011100101100 -
b100000 /
0%
b1 #
b1 +
b100010 *
#195000
b11110100001100011101110010110000 -
b100000 /
b10000010111100111000100011010011 "
b10000010111100111000100011010011 ,
b1111101000011000111011100101100 .
1%
#200000
b11111101101100111110011111011110 -
b100000 /
0%
b11 #
b11 +
b100100 *
#205000
b11110110110011111001111101111000 -
b100000 /
b10010011000001100000100001 "
b10010011000001100000100001 ,
b11111101101100111110011111011110 .
1%
#210000
b11111111010011011010010000010110 -
b100000 /
0%
b1 #
b1 +
b100110 *
#215000
b11110100101101001010101100110110 -
b100000 /
b101100100101101111101001 "
b101100100101101111101001 ,
b11111111010011011010010000010110 .
1%
#220000
0%
b101000 *
#225000
b11011011010100001001011110110110 -
b100000 /
b1011010010110101010011001001 "
b1011010010110101010011001001 ,
b11110100101101001010101100110110 .
1%
#230000
b11010010110100101010110011011000 -
b100000 /
0%
b11 #
b11 +
b101010 *
#235000
b1001011010010101011001101100000 -
b100000 /
b101101001011010101001100100111 "
b101101001011010101001100100111 ,
b11010010110100101010110011011000 .
1%
#240000
b1001111100010111010111011010111 -
b100000 /
0%
b10 #
b10 +
b101100 *
#245000
b110011011011011001110110000101 -
b100000 /
b10110000011101000101000100101000 "
b10110000011101000101000100101000 ,
b1001111100010111010111011010111 .
1%
#250000
b111010111011111010011011101011 -
b100000 /
0%
b0 #
b0 +
b101110 *
#255000
b11101011101111101001101110101100 -
b100000 /
b11000101000100000101100100010100 "
b11000101000100000101100100010100 ,
b111010111011111010011011101011 .
1%
#260000
b11101111011111111000011000011011 -
b100000 /
0%
b1 #
b1 +
b110000 *
#265000
b10110100011111000010001100000010 -
b100000 /
b10000100000000111100111100100 "
b10000100000000111100111100100 ,
b11101111011111111000011000011011 .
1%
#270000
0%
b110010 *
#275000
b11011100101100111010101011010001 -
b100000 /
b1001011100000111101110011111101 "
b1001011100000111101110011111101 ,
b10110100011111000010001100000010 .
1%
#280000
b11010001111100001000110000001000 -
b100000 /
0%
b10 #
b10 +
b110100 *
#285000
b1000011000000110010110110010111 -
b100000 /
b101110000011110111001111110111 "
b101110000011110111001111110111 ,
b11010001111100001000110000001000 .
1%
#290000
0%
b110110 *
#295000
b1010011111001000010000101 -
b100000 /
b10111100111111001101001001101000 "
b10111100111111001101001001101000 ,
b1000011000000110010110110010111 .
1%
#300000
b1100000011001011011001011100 -
b100000 /
0%
b1 #
b1 +
b111000 *
#305000
b110100111100111100010011000111 -
b100000 /
b11110011111100110100100110100011 "
b11110011111100110100100110100011 ,
b1100000011001011011001011100 .
1%
#310000
0%
b111010 *
#315000
b11010111000011100000111010101011 -
b100000 /
b11001011000011000011101100111000 "
b11001011000011000011101100111000 ,
b110100111100111100010011000111 .
1%
#320000
b11011010010011010010100001110010 -
b100000 /
0%
b10 #
b10 +
b111100 *
#325000
b1101101111101011011110001111111 -
b100000 /
b100101101100101101011110001101 "
b100101101100101101011110001101 ,
b11011010010011010010100001110010 .
1%
#330000
b1101001001101001010000111001000 -
b100000 /
0%
b11 #
b11 +
b111110 *
#335000
b10101101010100001011110001001110 -
b100000 /
b10010110110010110101111000110111 "
b10010110110010110101111000110111 ,
b1101001001101001010000111001000 .
1%
#340000
b10100000000100111001101010010111 -
b100000 /
0%
0$
b0 #
b0 +
b0 *
#345000
1%
#350000
0%
b1 *
#355000
1%
#360000
0%
1(
b10 *
#365000
b11110010101111001101100100100101 -
b100000 /
b0 "
b0 ,
b11111111111111111111111111111111 .
1%
#370000
0%
0(
#375000
1%
#380000
b11110110011111011100010010010010 -
b100000 /
0%
b1 #
b1 +
1$
b0 *
#385000
b11010000011101010010100100100110 -
b100000 /
b1001100000100011101101101101 "
b1001100000100011101101101101 ,
b11110110011111011100010010010010 .
1%
#390000
b11011101001101100000111111111111 -
b100000 /
0%
b10 #
b10 +
b10 *
#395000
b1110000000110010010001001001011 -
b100000 /
b100010110010011111000000000000 "
b100010110010011111000000000000 ,
b11011101001101100000111111111111 .
1%
#400000
b1111101010110100000010010010010 -
b100000 /
0%
b1 #
b1 +
b100 *
#405000
b11110101011010000001001001001000 -
b100000 /
b10000010101001011111101101101101 "
b10000010101001011111101101101101 ,
b1111101010110100000010010010010 .
1%
#410000
b11111100111010100010100100100110 -
b100000 /
0%
b11 #
b11 +
b110 *
#415000
b11110011101010001010010010011000 -
b100000 /
b11000101011101011011011001 "
b11000101011101011011011001 ,
b11111100111010100010100100100110 .
1%
#420000
b11111010001010101001111111110110 -
b100000 /
0%
b1 #
b1 +
b1000 *
#425000
b11100001001010000100010010110110 -
b100000 /
b101110101010110000000001001 "
b101110101010110000000001001 ,
b11111010001010101001111111110110 .
1%
#430000
b11101100011010110110001001101111 -
b100000 /
0%
b10 #
b10 +
b1010 *
#435000
b10110101011011001001010000001011 -
b100000 /
b10011100101001001110110010000 "
b10011100101001001110110010000 ,
b11101100011010110110001001101111 .
1%
#440000
0%
b1100 *
#445000
b11010101101100100101000000101100 -
b100000 /
b1001010100100110110101111110100 "
b1001010100100110110101111110100 ,
b10110101011011001001010000001011 .
1%
#450000
b11011000111100010111011011110101 -
b100000 /
0%
b1 #
b1 +
b1110 *
#455000
b1101010010001111110000010111010 -
b100000 /
b100111000011101000100100001010 "
b100111000011101000100100001010 ,
b11011000111100010111011011110101 .
1%
#460000
0%
b10000 *
#465000
b10101001000111111000001011101000 -
b100000 /
b10010101101110000001111101000101 "
b10010101101110000001111101000101 ,
b1101010010001111110000010111010 .
1%
#470000
b10100100010111001010010000110001 -
b100000 /
0%
b10 #
b10 +
b10010 *
#475000
b10010001011100101001000011000100 -
b100000 /
b1011011101000110101101111001110 "
b1011011101000110101101111001110 ,
b10100100010111001010010000110001 .
1%
#480000
b10011000111100001010101110101010 -
b100000 /
0%
b0 #
b0 +
b10100 *
#485000
b1101010010000001001010111000110 -
b100000 /
b1100111000011110101010001010101 "
b1100111000011110101010001010101 ,
b10011000111100001010101110101010 .
1%
#490000
0%
b10110 *
#495000
b10101101110000110100101010101111 -
b100000 /
b10010101101111110110101000111001 "
b10010101101111110110101000111001 ,
b1101010010000001001010111000110 .
1%
#500000
b10100000100000000110110001110110 -
b100000 /
0%
b11 #
b11 +
b11000 *
#505000
b10000110110000001010110001101111 -
b100000 /
b1011111011111111001001110001001 "
b1011111011111111001001110001001 ,
b10100000100000000110110001110110 .
1%
#510000
b10001111010000101001011100000001 -
b100000 /
0%
b1 #
b1 +
b11010 *
#515000
b110000010010010111101011011101 -
b100000 /
b1110000101111010110100011111110 "
b1110000101111010110100011111110 ,
b10001111010000101001011100000001 .
1%
#520000
b110100100010000110011101101010 -
b100000 /
0%
b0 #
b0 +
b11100 *
#525000
b11010010001000011001110110101000 -
b100000 /
b11001011011101111001100010010101 "
b11001011011101111001100010010101 ,
b110100100010000110011101101010 .
1%
#530000
b11010110111000001000000000011111 -
b100000 /
0%
b1 #
b1 +
b11110 *
#535000
b1010010000000000011101100010010 -
b100000 /
b101001000111110111111111100000 "
b101001000111110111111111100000 ,
b11010110111000001000000000011111 .
1%
#540000
b1011111010000110001110111001011 -
b100000 /
0%
b10 #
b10 +
b100000 *
#545000
b1110000010011110101000111110101 -
b100000 /
b10100000101111001110001000110100 "
b10100000101111001110001000110100 ,
b1011111010000110001110111001011 .
1%
#550000
b1111101000011000111011100101100 -
b100000 /
0%
b1 #
b1 +
b100010 *
#555000
b11110100001100011101110010110000 -
b100000 /
b10000010111100111000100011010011 "
b10000010111100111000100011010011 ,
b1111101000011000111011100101100 .
1%
#560000
b11111101101100111110011111011110 -
b100000 /
0%
b11 #
b11 +
b100100 *
#565000
b11110110110011111001111101111000 -
b100000 /
b10010011000001100000100001 "
b10010011000001100000100001 ,
b11111101101100111110011111011110 .
1%
#570000
b11111111010011011010010000010110 -
b100000 /
0%
b1 #
b1 +
b100110 *
#575000
b11110100101101001010101100110110 -
b100000 /
b101100100101101111101001 "
b101100100101101111101001 ,
b11111111010011011010010000010110 .
1%
#580000
0%
b101000 *
#585000
b11011011010100001001011110110110 -
b100000 /
b1011010010110101010011001001 "
b1011010010110101010011001001 ,
b11110100101101001010101100110110 .
1%
#590000
b11010010110100101010110011011000 -
b100000 /
0%
b11 #
b11 +
b101010 *
#595000
b1001011010010101011001101100000 -
b100000 /
b101101001011010101001100100111 "
b101101001011010101001100100111 ,
b11010010110100101010110011011000 .
1%
#600000
b1001111100010111010111011010111 -
b100000 /
0%
b10 #
b10 +
b101100 *
#605000
b110011011011011001110110000101 -
b100000 /
b10110000011101000101000100101000 "
b10110000011101000101000100101000 ,
b1001111100010111010111011010111 .
1%
#610000
b111010111011111010011011101011 -
b100000 /
0%
b0 #
b0 +
b101110 *
#615000
b11101011101111101001101110101100 -
b100000 /
b11000101000100000101100100010100 "
b11000101000100000101100100010100 ,
b111010111011111010011011101011 .
1%
#620000
b11101111011111111000011000011011 -
b100000 /
0%
b1 #
b1 +
b110000 *
#625000
b10110100011111000010001100000010 -
b100000 /
b10000100000000111100111100100 "
b10000100000000111100111100100 ,
b11101111011111111000011000011011 .
1%
#630000
0%
b110010 *
#635000
b11011100101100111010101011010001 -
b100000 /
b1001011100000111101110011111101 "
b1001011100000111101110011111101 ,
b10110100011111000010001100000010 .
1%
#640000
b11010001111100001000110000001000 -
b100000 /
0%
b10 #
b10 +
b110100 *
#645000
b1000011000000110010110110010111 -
b100000 /
b101110000011110111001111110111 "
b101110000011110111001111110111 ,
b11010001111100001000110000001000 .
1%
#650000
0%
b110110 *
#655000
b1010011111001000010000101 -
b100000 /
b10111100111111001101001001101000 "
b10111100111111001101001001101000 ,
b1000011000000110010110110010111 .
1%
#660000
b1100000011001011011001011100 -
b100000 /
0%
b1 #
b1 +
b111000 *
#665000
b110100111100111100010011000111 -
b100000 /
b11110011111100110100100110100011 "
b11110011111100110100100110100011 ,
b1100000011001011011001011100 .
1%
#670000
0%
b111010 *
#675000
b11010111000011100000111010101011 -
b100000 /
b11001011000011000011101100111000 "
b11001011000011000011101100111000 ,
b110100111100111100010011000111 .
1%
#680000
b11011010010011010010100001110010 -
b100000 /
0%
b10 #
b10 +
b111100 *
#685000
b1101101111101011011110001111111 -
b100000 /
b100101101100101101011110001101 "
b100101101100101101011110001101 ,
b11011010010011010010100001110010 .
1%
#690000
b1101001001101001010000111001000 -
b100000 /
0%
b11 #
b11 +
b111110 *
#695000
b10101101010100001011110001001110 -
b100000 /
b10010110110010110101111000110111 "
b10010110110010110101111000110111 ,
b1101001001101001010000111001000 .
1%
#700000
b10101001100100011010000111111001 -
b100000 /
0%
b10 #
b10 +
b10010110110010110101111000110111 '
b0 *
#705000
b10100110010001101000011111100100 -
b100000 /
b1010110011011100101111000000110 "
b1010110011011100101111000000110 ,
b10101001100100011010000111111001 .
1%
#710000
b10101011000001011010000100111101 -
b100000 /
0%
b1 #
b1 +
b10 *
#715000
b10100001010101011010001000101101 -
b100000 /
b1010100111110100101111011000010 "
b1010100111110100101111011000010 ,
b10101011000001011010000100111101 .
1%
#720000
0%
b100 *
#725000
b10001000000101011010111001101101 -
b100000 /
b1011110101010100101110111010010 "
b1011110101010100101110111010010 ,
b10100001010101011010001000101101 .
1%
#730000
b10000101010101101000100010110100 -
b100000 /
0%
b10 #
b10 +
b110 *
#735000
b10101010110100010001011010000 -
b100000 /
b1111010101010010111011101001011 "
b1111010101010010111011101001011 ,
b10000101010101101000100010110100 .
1%
#740000
b10001100110110011111101100111 -
b100000 /
0%
b11 #
b11 +
b1000 *
#745000
b1001011001011111101101101000101 -
b100000 /
b11101110011001001100000010011000 "
b11101110011001001100000010011000 ,
b10001100110110011111101100111 .
1%
#750000
b1000110011011001111110110011100 -
b100000 /
0%
b0 #
b0 +
b1010 *
#755000
b11101011100101110101111000111 -
b100000 /
b10111001100100110000001001100011 "
b10111001100100110000001001100011 ,
b1000110011011001111110110011100 .
1%
#760000
b10100111100001101000010101001 -
b100000 /
0%
b10 #
b10 +
b1100 *
#765000
b1011010010000010111100111001010 -
b100000 /
b11101011000011110010111101010110 "
b11101011000011110010111101010110 ,
b10100111100001101000010101001 .
1%
#770000
b1011110100000000110010001111101 -
b100000 /
0%
b11 #
b11 +
b1110 *
#775000
b1110011100000111010101010011010 -
b100000 /
b10100001011111111001101110000010 "
b10100001011111111001101110000010 ,
b1011110100000000110010001111101 .
1%
#780000
b1111010000000011001000111110100 -
b100000 /
0%
b1 #
b1 +
b10000 *
#785000
b11101000000001100100011111010000 -
b100000 /
b10000101111111100110111000001011 "
b10000101111111100110111000001011 ,
b1111010000000011001000111110100 .
1%
#790000
0%
b10010 *
#795000
b10101001100110110010010000101110 -
b100000 /
b10111111110011011100000101111 "
b10111111110011011100000101111 ,
b11101000000001100100011111010000 .
1%
#800000
b10100000000110010001111101000000 -
b100000 /
0%
b11 #
b11 +
b10100 *
#805000
b10000100101001010110000010110111 -
b100000 /
b1011111111001101110000010111111 "
b1011111111001101110000010111111 ,
b10100000000110010001111101000000 .
1%
#810000
b10000000011001000111110100000000 -
b100000 /
0%
b10 #
b10 +
b10110 *
#815000
b1100100011111010000000000 -
b100000 /
b1111111100110111000001011111111 "
b1111111100110111000001011111111 ,
b10000000011001000111110100000000 .
1%
#820000
b1000000100111100111101101110 -
b100000 /
0%
b0 #
b0 +
b11000 *
#825000
b100000010011110011110110111000 -
b100000 /
b11110111111011000011000010010001 "
b11110111111011000011000010010001 ,
b1000000100111100111101101110 .
1%
#830000
b101101000011000001101101100001 -
b100000 /
0%
b11 #
b11 +
b11010 *
#835000
b10111001011100110100101101011101 -
b100000 /
b11010010111100111110010010011110 "
b11010010111100111110010010011110 ,
b101101000011000001101101100001 .
1%
#840000
b10110000111100010111000000110011 -
b100000 /
0%
b1 #
b1 +
b11100 *
#845000
b11001110100001101110011000010101 -
b100000 /
b1001111000011101000111111001100 "
b1001111000011101000111111001100 ,
b10110000111100010111000000110011 .
1%
#850000
b11000111000001001101110101111011 -
b100000 /
0%
b11 #
b11 +
b11110 *
#855000
b11100000100110111010111101100 -
b100000 /
b111000111110110010001010000100 "
b111000111110110010001010000100 ,
b11000111000001001101110101111011 .
1%
#860000
b10001010100000101001100110101 -
b100000 /
0%
0$
b0 #
b0 +
b0 *
#865000
1%
#870000
0%
b1 *
#875000
1%
#880000
0%
b10 *
