testing/pset5/src/lfsr_4.sv
module lfsr_4 ( input wire clk_in, input wire rst_in,
                    input wire [3:0] seed_in,
                    output logic [3:0] q_out);

logic q1, q2, q3, q4; // Initialize the registers

always_ff@(posedge clk_in) begin
	if (rst_in) begin
		q1 <= seed_in[0];
		q2 <= seed_in[1];
		q3 <= seed_in[2];
		q4 <= seed_in[3];
		q_out <= seed_in;
	end else begin
		q_out <= {q3, q2, q1 ^ q4, q4};
		q1 <= q4;
		q2 <= q1 ^ q4;
		q3 <= q2;
		q4 <= q3;
	end
end

endmodule

testing/pset5/sim/lfsr_4_tb.sv
`timescale 1ns / 1ps
`default_nettype none

module lfsr_4_tb;

  //make logics for inputs and outputs!
  logic clk_in;
  logic rst_in;
  logic [3:0] seed_in;
  logic [3:0] q_out;

  lfsr_4 uut (.clk_in(clk_in),
            .rst_in(rst_in),
            .seed_in(seed_in),
            .q_out(q_out));

  always begin
    #5;  //every 5 ns switch...so period of clock is 10 ns...100 MHz clock
    clk_in = !clk_in;
  end

  //initial block...this is our test simulation
  initial begin
    $dumpfile("lfsr_4.vcd"); //file to store value change dump (vcd)
    $dumpvars(0,lfsr_4_tb); //store everything at the current level and below
    $display("Starting Sim"); //print nice message
    clk_in = 0; //initialize clk (super important)
    rst_in = 0; //initialize rst (super important)
    seed_in = 4'b0101;
    #10  //wait a little bit of time at beginning
    rst_in = 1; //reset system
    #10; //hold high for a few clock cycles
    rst_in=0;
    for (int i = 0; i<30; i= i+1)begin
      $display("%4b",q_out);
      #10;
    end
    $finish;

  end
endmodule //counter_tb

`default_nettype wire

testing/pset5/lfsr_4.vcd
$date
	Sun Sep 25 04:37:43 2022
$end
$version
	Icarus Verilog
$end
$timescale
	1ps
$end
$scope module lfsr_4_tb $end
$var wire 4 ! q_out [3:0] $end
$var reg 1 " clk_in $end
$var reg 1 # rst_in $end
$var reg 4 $ seed_in [3:0] $end
$scope module uut $end
$var wire 1 " clk_in $end
$var wire 1 # rst_in $end
$var wire 4 % seed_in [3:0] $end
$var reg 1 & q1 $end
$var reg 1 ' q2 $end
$var reg 1 ( q3 $end
$var reg 1 ) q4 $end
$var reg 4 * q_out [3:0] $end
$upscope $end
$scope begin $ivl_for_loop0 $end
$var integer 32 + i [31:0] $end
$upscope $end
$upscope $end
$enddefinitions $end
#0
$dumpvars
b0 +
bx *
x)
x(
x'
x&
b101 %
b101 $
0#
0"
bx !
$end
#5000
1"
#10000
0"
1#
#15000
b101 !
b101 *
0)
1(
0'
1&
1"
#20000
0"
0#
#25000
1)
0(
1'
0&
b1010 !
b1010 *
1"
#30000
0"
b1 +
#35000
0)
1(
1&
b111 !
b111 *
1"
#40000
0"
b10 +
#45000
1)
0&
b1110 !
b1110 *
1"
#50000
0"
b11 +
#55000
1&
b1111 !
b1111 *
1"
#60000
0"
b100 +
#65000
0'
b1101 !
b1101 *
1"
#70000
0"
b101 +
#75000
0(
b1001 !
b1001 *
1"
#80000
0"
b110 +
#85000
0)
b1 !
b1 *
1"
#90000
0"
b111 +
#95000
1'
0&
b10 !
b10 *
1"
#100000
0"
b1000 +
#105000
1(
0'
b100 !
b100 *
1"
#110000
0"
b1001 +
#115000
1)
0(
b1000 !
b1000 *
1"
#120000
0"
b1010 +
#125000
0)
1'
1&
b11 !
b11 *
1"
#130000
0"
b1011 +
#135000
1(
0&
b110 !
b110 *
1"
#140000
0"
b1100 +
#145000
1)
0'
b1100 !
b1100 *
1"
#150000
0"
b1101 +
#155000
0(
1'
1&
b1011 !
b1011 *
1"
#160000
0"
b1110 +
#165000
0)
1(
0'
b101 !
b101 *
1"
#170000
0"
b1111 +
#175000
1)
0(
1'
0&
b1010 !
b1010 *
1"
#180000
0"
b10000 +
#185000
0)
1(
1&
b111 !
b111 *
1"
#190000
0"
b10001 +
#195000
1)
0&
b1110 !
b1110 *
1"
#200000
0"
b10010 +
#205000
1&
b1111 !
b1111 *
1"
#210000
0"
b10011 +
#215000
0'
b1101 !
b1101 *
1"
#220000
0"
b10100 +
#225000
0(
b1001 !
b1001 *
1"
#230000
0"
b10101 +
#235000
0)
b1 !
b1 *
1"
#240000
0"
b10110 +
#245000
1'
0&
b10 !
b10 *
1"
#250000
0"
b10111 +
#255000
1(
0'
b100 !
b100 *
1"
#260000
0"
b11000 +
#265000
1)
0(
b1000 !
b1000 *
1"
#270000
0"
b11001 +
#275000
0)
1'
1&
b11 !
b11 *
1"
#280000
0"
b11010 +
#285000
1(
0&
b110 !
b110 *
1"
#290000
0"
b11011 +
#295000
1)
0'
b1100 !
b1100 *
1"
#300000
0"
b11100 +
#305000
0(
1'
1&
b1011 !
b1011 *
1"
#310000
0"
b11101 +
#315000
0)
1(
0'
b101 !
b101 *
1"
#320000
0"
b11110 +
